Workbook

Sheet Organismo
E1: Tipo de Nómina | F1: Periodicidad de Pago | G1: Fecha de Pago | H1: Fecha Inicial de pago | I1: Fecha Final de pago | J1: Clave Periodicidad de Pago | K1: Clave Tipo de Nómina | L1: Numero de días pagados | M1: Nómina Sindicalizada
B2: Versión | C2: 3.3 | E2: Nómina Ordinaria | F2: Mensual | G2: 44330 | H2: 44317 | I2: 44347 | J2: =IF(TablaOrganismo[Periodicidad de Pago]="","",VLOOKUP(TablaOrganismo[Periodicidad de Pago],Cat!$D$1:$E$12,2,0)) -> 5 | K2: =IF(TablaOrganismo[Tipo de Nómina]="","",VLOOKUP(TablaOrganismo[Tipo de Nómina],Cat!$A$2:$B$3,2,0)) -> O | L2: =IF(OR(TablaOrganismo[Fecha Inicial de pago]>TablaOrganismo[Fecha Final de pago],TablaOrganismo[Fecha Inicial de pago]="",TablaOrganismo[Fecha Final de pago]=""),"",TablaOrganismo[Fecha Final de pago]-TablaOrganismo[Fecha Inicial de pago]+1) -> 31 | M2: No
B3: Serie | C3: =CONCATENATE(COUNT(TablaTrabajadores[[#All],[Número de Empleado]]),IF(TablaOrganismo[Nómina Sindicalizada]="No","C","S"),IFERROR(IF(FIND(" ",E4)>0,LEFT(E4,1)&MID(E4,FIND(" ",E4)+1,1)),LEFT(E4,1)),TEXT(TablaOrganismo[Fecha de Pago],"aaaa"),TEXT(TablaOrganismo[Fecha de Pago],"mmm"),IF(TEXT(TablaOrganismo[Fecha de Pago],"dd")="15","1era","2da"),TablaOrganismo[Clave Tipo de Nómina]) -> 18CO2021may2daO
B4: Forma de Pago | C4: 99 | E4: O
B5: Método de Pago | C5: N
B6: Tipo de Comprobante | C6: PUE
B7: Moneda | C7: MXN
B8: Código Postal | C8: 29039
B9: RFC del Organismo | C9: SCR0103101R0
B10: Nombre del Organismo | C10: SISTEMA CHIAPANECO DE RADIO, TELEVISIÓN Y CINEMATOGRAFÍA
B11: Régimen Fiscal del Organismo | C11: 603
B12: Registro Patronal del Organismo | C12: A6831083386
B13: Régimen Fiscal del Organismo | C13: Personas Morales con Fines no Lucrativos

Sheet Trabajadores
A1: Consecutivo Trabajador | B1: RFC Trabajador | C1: Nombre Trabajador | D1: CURP | E1: NSS | F1: Fecha Inicio Relación Laboral | G1: Tipo de Contrato | H1: Tipo de Régimen | I1: Número de Empleado | J1: Departamento | K1: Puesto | L1: Riesgo de Puesto | M1: Salario Diario Integrado | N1: Origen del Recurso | O1: Monto Recurso Propio | P1: Entidad Federativa | Q1: Correo Electrónico | R1: CC | S1: CCO | T1: Clave Tipo de Contrato | U1: Clave Tipo de Régimen | V1: Total de Percepciones | W1: Total de Deducciones | X1: Total de Otros Pagos | Y1: Antigüedad | Z1: ConteoPercepciones | AA1: ConteoDeducciones | AB1: Total Gravado | AC1: Total Exento | AD1: Total Otras Deducciones | AE1: Total Impuestos Retenidos | AF1: ClaveOrigen del Recurso2 | AG1: ClaveEntidadFederativa | AH1: ConteoHorasExtra | AI1: ConteOtrosPagos | AJ1: ClaveJornada | AK1: TotalSueldos | AL1: TotalSeparacionIndemnizacion | AM1: TotalJubilacionPensionRetiro | AN1: Tipo de Jornada
A2: 1 | B2: CAOA900910AZ9 | C2: CAMACHO OVANDO ALAN ULISES | D2: CAOA900910HCSMVL04 | E2: 71089008313 | F2: 42826 | G2: Contrato de trabajo por tiempo indeterminado | H2: Sueldos | I2: 967 | J2: AREA DE RECURSOS MATERIALES | K2: VELADOR | L2: 1 | M2: 157.26603 | N2: Ingresos propios | P2: Chiapas | Q2: camacho.ovando@hotmail.com | R2: canal10humanos@gmail.com | T2: =IF(TablaTrabajadores[[#This Row],[Tipo de Contrato]]="","",VLOOKUP(TablaTrabajadores[[#This Row],[Tipo de Contrato]],Cat!$G$1:$H$12,2,0)) -> 1 | U2: =IF(TablaTrabajadores[[#This Row],[Tipo de Régimen]]="","",VLOOKUP(TablaTrabajadores[[#This Row],[Tipo de Régimen]],Cat!$J$1:$K$13,2,0)) -> 2 | V2: =ROUND(IF((SUMIF(TablaPercepciones[[#All],[Trabajador]],TablaTrabajadores[[#This Row],[Nombre Trabajador]],TablaPercepciones[[#All],[Importe Gravado]])+SUMIF(TablaPercepciones[[#All],[Trabajador]],TablaTrabajadores[[#This Row],[Nombre Trabajador]],TablaPercepciones[[#All],[o]]))=0,0,SUMIF(TablaPercepciones[[#All],[Trabajador]],TablaTrabajadores[[#This Row],[Nombre Trabajador]],TablaPercepciones[[#All],[Importe Gravado]])+SUMIF(TablaPercepciones[[#All],[Trabajador]],TablaTrabajadores[[#This Row],[Nombre Trabajador]],TablaPercepciones[[#All],[o]])),2) -> #REF! | W2: =ROUND(IF((SUMIF(TablaDeducciones[[#All],[Trabajador]],TablaTrabajadores[[#This Row],[Nombre Trabajador]],TablaDeducciones[[#All],[Importe]]))=0,0,SUMIF(TablaDeducciones[[#All],[Trabajador]],TablaTrabajadores[[#This Row],[Nombre Trabajador]],TablaDeducciones[[#All],[Importe]])),2) -> #REF! | X2: =ROUND(IF((SUMIF(TablaOtrosPagos[[#All],[Trabajador]],TablaTrabajadores[[#This Row],[Nombre Trabajador]],TablaOtrosPagos[[#All],[Importe]]))=0,0,SUMIF(TablaOtrosPagos[[#All],[Trabajador]],TablaTrabajadores[[#This Row],[Nombre Trabajador]],TablaOtrosPagos[[#All],[Importe]])),2) -> #REF! | Y2: =IF(OR(TablaOrganismo[Fecha Final de pago]="",TablaTrabajadores[[#This Row],[Fecha Inicio Relación Laboral]]=""),"",CONCATENATE("P",ROUNDDOWN((TablaOrganismo[Fecha Final de pago]-TablaTrabajadores[[#This Row],[Fecha Inicio Relación Laboral]])/7,0),"W")) -> P217W | Z2: =COUNTIF(TablaPercepciones[[#All],[Trabajador]],TablaTrabajadores[[#This Row],[Nombre Trabajador]]) -> 4 | AA2: =COUNTIF(TablaDeducciones[[#All],[Trabajador]],TablaTrabajadores[[#This Row],[Nombre Trabajador]]) -> 2 | AB2: =ROUND(IF((SUMIF(TablaPercepciones[[#All],[Trabajador]],TablaTrabajadores[[#This Row],[Nombre Trabajador]],TablaPercepciones[[#All],[Importe Gravado]]))=0,0,SUMIF(TablaPercepciones[[#All],[Trabajador]],TablaTrabajadores[[#This Row],[Nombre Trabajador]],TablaPercepciones[[#All],[Importe Gravado]])),2) -> #REF! | AC2: =ROUND(IF((SUMIF(TablaPercepciones[[#All],[Trabajador]],TablaTrabajadores[[#This Row],[Nombre Trabajador]],TablaPercepciones[[#All],[o]]))=0,0,SUMIF(TablaPercepciones[[#All],[Trabajador]],TablaTrabajadores[[#This Row],[Nombre Trabajador]],TablaPercepciones[[#All],[o]])),2) -> #REF! | AD2: =ROUND(IF(SUMIFS(TablaDeducciones[[#All],[Importe]],TablaDeducciones[[#All],[Trabajador]],TablaTrabajadores[[#This Row],[Nombre Trabajador]],TablaDeducciones[[#All],[Clave Deducción]],"<>002")=0,0,SUMIFS(TablaDeducciones[[#All],[Importe]],TablaDeducciones[[#All],[Trabajador]],TablaTrabajadores[[#This Row],[Nombre Trabajador]],TablaDeducciones[[#All],[Clave Deducción]],"<>002")),2) -> #REF! | AE2: =ROUND(IF((SUMIFS(TablaDeducciones[[#All],[Importe]],TablaDeducciones[[#All],[Trabajador]],TablaTrabajadores[[#This Row],[Nombre Trabajador]],TablaDeducciones[[#All],[Clave Deducción]],"=002"))=0,0,SUMIFS(TablaDeducciones[[#All],[Importe]],TablaDeducciones[[#All],[Trabajador]],TablaTrabajadores[[#This Row],[Nombre Trabajador]],TablaDeducciones[[#All],[Clave Deducción]],"=002")),2) -> 0 | AF2: =IF(TablaTrabajadores[[#This Row],[Origen del Recurso]]="","",VLOOKUP(TablaTrabajadores[[#This Row],[Origen del Recurso]],Cat!Y:Z,2,0)) -> IP | AG2: =IF(TablaTrabajadores[[#This Row],[Entidad Federativa]]="","",VLOOKUP(TablaTrabajadores[[#This Row],[Entidad Federativa]],Cat!AB:AC,2,0)) -> CHP | AH2: =COUNTIF(TablaHorasExtra[[#All],[Trabajador]],TablaTrabajadores[[#This Row],[Nombre Trabajador]]) -> 0 | AI2: =COUNTIF(TablaOtrosPagos[[#All],[Trabajador]],TablaTrabajadores[[#This Row],[Nombre Trabajador]]) -> 1 | AJ2: =IF(TablaTrabajadores[[#This Row],[Tipo de Jornada]]="","",VLOOKUP(TablaTrabajadores[[#This Row],[Tipo de Jornada]],Cat!AK:AL,2,0)) -> 1 | AK2: =ROUND(IFERROR(SUMIFS(TablaPercepciones[[#All],[Importe Gravado]],TablaPercepciones[[#All],[Trabajador]],TablaTrabajadores[[#This Row],[Nombre Trabajador]],TablaPercepciones[[#All],[Clave Percepción]],"<>022",TablaPercepciones[[#All],[Clave Percepción]],"<>023",TablaPercepciones[[#All],[Clave Percepción]],"<>025",TablaPercepciones[[#All],[Clave Percepción]],"<>044"),0)+IFERROR(SUMIFS(TablaPercepciones[[#All],[o]],TablaPercepciones[[#All],[Trabajador]],TablaTrabajadores[[#This Row],[Nombre Trabajador]],TablaPercepciones[[#All],[Clave Percepción]],"<>022",TablaPercepciones[[#All],[Clave Percepción]],"<>023",TablaPercepciones[[#All],[Clave Percepción]],"<>025",TablaPercepciones[[#All],[Clave Percepción]],"<>044"),0),2) -> 0 | AL2: =ROUND(IFERROR(SUMIFS(TablaPercepciones[[#All],[Importe Gravado]],TablaPercepciones[[#All],[Trabajador]],TablaTrabajadores[[#This Row],[Nombre Trabajador]],TablaPercepciones[[#All],[Clave Percepción]],"=022"),0)+IFERROR(SUMIFS(TablaPercepciones[[#All],[Importe Gravado]],TablaPercepciones[[#All],[Trabajador]],TablaTrabajadores[[#This Row],[Nombre Trabajador]],TablaPercepciones[[#All],[Clave Percepción]],"=023"),0)+IFERROR(SUMIFS(TablaPercepciones[[#All],[Importe Gravado]],TablaPercepciones[[#All],[Trabajador]],TablaTrabajadores[[#This Row],[Nombre Trabajador]],TablaPercepciones[[#All],[Clave Percepción]],"=025"),0)+IFERROR(SUMIFS(TablaPercepciones[[#All],[o]],TablaPercepciones[[#All],[Trabajador]],TablaTrabajadores[[#This Row],[Nombre Trabajador]],TablaPercepciones[[#All],[Clave Percepción]],"=022"),0)+IFERROR(SUMIFS(TablaPercepciones[[#All],[o]],TablaPercepciones[[#All],[Trabajador]],TablaTrabajadores[[#This Row],[Nombre Trabajador]],TablaPercepciones[[#All],[Clave Percepción]],"=023"),0)+IFERROR(SUMIFS(TablaPercepciones[[#All],[o]],TablaPercepciones[[#All],[Trabajador]],TablaTrabajadores[[#This Row],[Nombre Trabajador]],TablaPercepciones[[#All],[Clave Percepción]],"=025"),0),2) -> 0 | AM2: =ROUND(IFERROR(SUMIFS(TablaPercepciones[[#All],[Importe Gravado]],TablaPercepciones[[#All],[Trabajador]],TablaTrabajadores[[#This Row],[Nombre Trabajador]],TablaPercepciones[[#All],[Clave Percepción]],"=039"),0)+IFERROR(SUMIFS(TablaPercepciones[[#All],[Importe Gravado]],TablaPercepciones[[#All],[Trabajador]],TablaTrabajadores[[#This Row],[Nombre Trabajador]],TablaPercepciones[[#All],[Clave Percepción]],"=044"),0)+IFERROR(SUMIFS(TablaPercepciones[[#All],[o]],TablaPercepciones[[#All],[Trabajador]],TablaTrabajadores[[#This Row],[Nombre Trabajador]],TablaPercepciones[[#All],[Clave Percepción]],"=039"),0)+IFERROR(SUMIFS(TablaPercepciones[[#All],[o]],TablaPercepciones[[#All],[Trabajador]],TablaTrabajadores[[#This Row],[Nombre Trabajador]],TablaPercepciones[[#All],[Clave Percepción]],"=044"),0),2) -> 0 | AN2: Diurna
A3: 2 | B3: EICS720717IA8 | C3: ENRIQUEZ CONSTANTINO SILVIA | D3: EICS720717MCSNNL07 | E3: 71907233135 | F3: 43891 | G3: Contrato de trabajo por tiempo indeterminado | H3: Sueldos | I3: 5184 | J3: RECURSOS MATERIALES | K3: VELADOR | L3: 1 | M3: 157.26603 | N3: Ingresos propios | P3: Chiapas | Q3: canal10humanos@gmail.com | R3: canal10humanos@gmail.com | T3: =IF(TablaTrabajadores[[#This Row],[Tipo de Contrato]]="","",VLOOKUP(TablaTrabajadores[[#This Row],[Tipo de Contrato]],Cat!$G$1:$H$12,2,0)) -> 1 | U3: =IF(TablaTrabajadores[[#This Row],[Tipo de Régimen]]="","",VLOOKUP(TablaTrabajadores[[#This Row],[Tipo de Régimen]],Cat!$J$1:$K$13,2,0)) -> 2 | V3: =ROUND(IF((SUMIF(TablaPercepciones[[#All],[Trabajador]],TablaTrabajadores[[#This Row],[Nombre Trabajador]],TablaPercepciones[[#All],[Importe Gravado]])+SUMIF(TablaPercepciones[[#All],[Trabajador]],TablaTrabajadores[[#This Row],[Nombre Trabajador]],TablaPercepciones[[#All],[o]]))=0,0,SUMIF(TablaPercepciones[[#All],[Trabajador]],TablaTrabajadores[[#This Row],[Nombre Trabajador]],TablaPercepciones[[#All],[Importe Gravado]])+SUMIF(TablaPercepciones[[#All],[Trabajador]],TablaTrabajadores[[#This Row],[Nombre Trabajador]],TablaPercepciones[[#All],[o]])),2) -> #REF! | W3: =ROUND(IF((SUMIF(TablaDeducciones[[#All],[Trabajador]],TablaTrabajadores[[#This Row],[Nombre Trabajador]],TablaDeducciones[[#All],[Importe]]))=0,0,SUMIF(TablaDeducciones[[#All],[Trabajador]],TablaTrabajadores[[#This Row],[Nombre Trabajador]],TablaDeducciones[[#All],[Importe]])),2) -> 0 | X3: =ROUND(IF((SUMIF(TablaOtrosPagos[[#All],[Trabajador]],TablaTrabajadores[[#This Row],[Nombre Trabajador]],TablaOtrosPagos[[#All],[Importe]]))=0,0,SUMIF(TablaOtrosPagos[[#All],[Trabajador]],TablaTrabajadores[[#This Row],[Nombre Trabajador]],TablaOtrosPagos[[#All],[Importe]])),2) -> #REF! | Y3: =IF(OR(TablaOrganismo[Fecha Final de pago]="",TablaTrabajadores[[#This Row],[Fecha Inicio Relación Laboral]]=""),"",CONCATENATE("P",ROUNDDOWN((TablaOrganismo[Fecha Final de pago]-TablaTrabajadores[[#This Row],[Fecha Inicio Relación Laboral]])/7,0),"W")) -> P65W | Z3: =COUNTIF(TablaPercepciones[[#All],[Trabajador]],TablaTrabajadores[[#This Row],[Nombre Trabajador]]) -> 4 | AA3: =COUNTIF(TablaDeducciones[[#All],[Trabajador]],TablaTrabajadores[[#This Row],[Nombre Trabajador]]) -> 0 | AB3: =ROUND(IF((SUMIF(TablaPercepciones[[#All],[Trabajador]],TablaTrabajadores[[#This Row],[Nombre Trabajador]],TablaPercepciones[[#All],[Importe Gravado]]))=0,0,SUMIF(TablaPercepciones[[#All],[Trabajador]],TablaTrabajadores[[#This Row],[Nombre Trabajador]],TablaPercepciones[[#All],[Importe Gravado]])),2) -> #REF! | AC3: =ROUND(IF((SUMIF(TablaPercepciones[[#All],[Trabajador]],TablaTrabajadores[[#This Row],[Nombre Trabajador]],TablaPercepciones[[#All],[o]]))=0,0,SUMIF(TablaPercepciones[[#All],[Trabajador]],TablaTrabajadores[[#This Row],[Nombre Trabajador]],TablaPercepciones[[#All],[o]])),2) -> #REF! | AD3: =ROUND(IF(SUMIFS(TablaDeducciones[[#All],[Importe]],TablaDeducciones[[#All],[Trabajador]],TablaTrabajadores[[#This Row],[Nombre Trabajador]],TablaDeducciones[[#All],[Clave Deducción]],"<>002")=0,0,SUMIFS(TablaDeducciones[[#All],[Importe]],TablaDeducciones[[#All],[Trabajador]],TablaTrabajadores[[#This Row],[Nombre Trabajador]],TablaDeducciones[[#All],[Clave Deducción]],"<>002")),2) -> 0 | AE3: =ROUND(IF((SUMIFS(TablaDeducciones[[#All],[Importe]],TablaDeducciones[[#All],[Trabajador]],TablaTrabajadores[[#This Row],[Nombre Trabajador]],TablaDeducciones[[#All],[Clave Deducción]],"=002"))=0,0,SUMIFS(TablaDeducciones[[#All],[Importe]],TablaDeducciones[[#All],[Trabajador]],TablaTrabajadores[[#This Row],[Nombre Trabajador]],TablaDeducciones[[#All],[Clave Deducción]],"=002")),2) -> 0 | AF3: =IF(TablaTrabajadores[[#This Row],[Origen del Recurso]]="","",VLOOKUP(TablaTrabajadores[[#This Row],[Origen del Recurso]],Cat!Y:Z,2,0)) -> IP | AG3: =IF(TablaTrabajadores[[#This Row],[Entidad Federativa]]="","",VLOOKUP(TablaTrabajadores[[#This Row],[Entidad Federativa]],Cat!AB:AC,2,0)) -> CHP | AH3: =COUNTIF(TablaHorasExtra[[#All],[Trabajador]],TablaTrabajadores[[#This Row],[Nombre Trabajador]]) -> 0 | AI3: =COUNTIF(TablaOtrosPagos[[#All],[Trabajador]],TablaTrabajadores[[#This Row],[Nombre Trabajador]]) -> 1 | AJ3: =IF(TablaTrabajadores[[#This Row],[Tipo de Jornada]]="","",VLOOKUP(TablaTrabajadores[[#This Row],[Tipo de Jornada]],Cat!AK:AL,2,0)) -> 1 | AK3: =ROUND(IFERROR(SUMIFS(TablaPercepciones[[#All],[Importe Gravado]],TablaPercepciones[[#All],[Trabajador]],TablaTrabajadores[[#This Row],[Nombre Trabajador]],TablaPercepciones[[#All],[Clave Percepción]],"<>022",TablaPercepciones[[#All],[Clave Percepción]],"<>023",TablaPercepciones[[#All],[Clave Percepción]],"<>025",TablaPercepciones[[#All],[Clave Percepción]],"<>044"),0)+IFERROR(SUMIFS(TablaPercepciones[[#All],[o]],TablaPercepciones[[#All],[Trabajador]],TablaTrabajadores[[#This Row],[Nombre Trabajador]],TablaPercepciones[[#All],[Clave Percepción]],"<>022",TablaPercepciones[[#All],[Clave Percepción]],"<>023",TablaPercepciones[[#All],[Clave Percepción]],"<>025",TablaPercepciones[[#All],[Clave Percepción]],"<>044"),0),2) -> 0 | AL3: =ROUND(IFERROR(SUMIFS(TablaPercepciones[[#All],[Importe Gravado]],TablaPercepciones[[#All],[Trabajador]],TablaTrabajadores[[#This Row],[Nombre Trabajador]],TablaPercepciones[[#All],[Clave Percepción]],"=022"),0)+IFERROR(SUMIFS(TablaPercepciones[[#All],[Importe Gravado]],TablaPercepciones[[#All],[Trabajador]],TablaTrabajadores[[#This Row],[Nombre Trabajador]],TablaPercepciones[[#All],[Clave Percepción]],"=023"),0)+IFERROR(SUMIFS(TablaPercepciones[[#All],[Importe Gravado]],TablaPercepciones[[#All],[Trabajador]],TablaTrabajadores[[#This Row],[Nombre Trabajador]],TablaPercepciones[[#All],[Clave Percepción]],"=025"),0)+IFERROR(SUMIFS(TablaPercepciones[[#All],[o]],TablaPercepciones[[#All],[Trabajador]],TablaTrabajadores[[#This Row],[Nombre Trabajador]],TablaPercepciones[[#All],[Clave Percepción]],"=022"),0)+IFERROR(SUMIFS(TablaPercepciones[[#All],[o]],TablaPercepciones[[#All],[Trabajador]],TablaTrabajadores[[#This Row],[Nombre Trabajador]],TablaPercepciones[[#All],[Clave Percepción]],"=023"),0)+IFERROR(SUMIFS(TablaPercepciones[[#All],[o]],TablaPercepciones[[#All],[Trabajador]],TablaTrabajadores[[#This Row],[Nombre Trabajador]],TablaPercepciones[[#All],[Clave Percepción]],"=025"),0),2) -> 0 | AM3: =ROUND(IFERROR(SUMIFS(TablaPercepciones[[#All],[Importe Gravado]],TablaPercepciones[[#All],[Trabajador]],TablaTrabajadores[[#This Row],[Nombre Trabajador]],TablaPercepciones[[#All],[Clave Percepción]],"=039"),0)+IFERROR(SUMIFS(TablaPercepciones[[#All],[Importe Gravado]],TablaPercepciones[[#All],[Trabajador]],TablaTrabajadores[[#This Row],[Nombre Trabajador]],TablaPercepciones[[#All],[Clave Percepción]],"=044"),0)+IFERROR(SUMIFS(TablaPercepciones[[#All],[o]],TablaPercepciones[[#All],[Trabajador]],TablaTrabajadores[[#This Row],[Nombre Trabajador]],TablaPercepciones[[#All],[Clave Percepción]],"=039"),0)+IFERROR(SUMIFS(TablaPercepciones[[#All],[o]],TablaPercepciones[[#All],[Trabajador]],TablaTrabajadores[[#This Row],[Nombre Trabajador]],TablaPercepciones[[#All],[Clave Percepción]],"=044"),0),2) -> 0 | AN3: Diurna
A4: 3 | B4: GOHS770725VE9 | C4: GOMEZ HERNANDEZ SANTIAGO CRISTOBAL | D4: GOHS770725HCSMRN04 | E4: 71937743913 | F4: 38169 | G4: Contrato de trabajo por tiempo indeterminado | H4: Sueldos | I4: 88 | J4: ESTACION TV SAN CRISTOBAL XHSBB TV | K4: VELADOR | L4: 1 | M4: 157.76034 | N4: Ingresos propios | P4: Chiapas | Q4: canal10humanos@gmail.com | R4: canal10humanos@gmail.com | T4: =IF(TablaTrabajadores[[#This Row],[Tipo de Contrato]]="","",VLOOKUP(TablaTrabajadores[[#This Row],[Tipo de Contrato]],Cat!$G$1:$H$12,2,0)) -> 1 | U4: =IF(TablaTrabajadores[[#This Row],[Tipo de Régimen]]="","",VLOOKUP(TablaTrabajadores[[#This Row],[Tipo de Régimen]],Cat!$J$1:$K$13,2,0)) -> 2 | V4: =ROUND(IF((SUMIF(TablaPercepciones[[#All],[Trabajador]],TablaTrabajadores[[#This Row],[Nombre Trabajador]],TablaPercepciones[[#All],[Importe Gravado]])+SUMIF(TablaPercepciones[[#All],[Trabajador]],TablaTrabajadores[[#This Row],[Nombre Trabajador]],TablaPercepciones[[#All],[o]]))=0,0,SUMIF(TablaPercepciones[[#All],[Trabajador]],TablaTrabajadores[[#This Row],[Nombre Trabajador]],TablaPercepciones[[#All],[Importe Gravado]])+SUMIF(TablaPercepciones[[#All],[Trabajador]],TablaTrabajadores[[#This Row],[Nombre Trabajador]],TablaPercepciones[[#All],[o]])),2) -> #REF! | W4: =ROUND(IF((SUMIF(TablaDeducciones[[#All],[Trabajador]],TablaTrabajadores[[#This Row],[Nombre Trabajador]],TablaDeducciones[[#All],[Importe]]))=0,0,SUMIF(TablaDeducciones[[#All],[Trabajador]],TablaTrabajadores[[#This Row],[Nombre Trabajador]],TablaDeducciones[[#All],[Importe]])),2) -> #REF! | X4: =ROUND(IF((SUMIF(TablaOtrosPagos[[#All],[Trabajador]],TablaTrabajadores[[#This Row],[Nombre Trabajador]],TablaOtrosPagos[[#All],[Importe]]))=0,0,SUMIF(TablaOtrosPagos[[#All],[Trabajador]],TablaTrabajadores[[#This Row],[Nombre Trabajador]],TablaOtrosPagos[[#All],[Importe]])),2) -> #REF! | Y4: =IF(OR(TablaOrganismo[Fecha Final de pago]="",TablaTrabajadores[[#This Row],[Fecha Inicio Relación Laboral]]=""),"",CONCATENATE("P",ROUNDDOWN((TablaOrganismo[Fecha Final de pago]-TablaTrabajadores[[#This Row],[Fecha Inicio Relación Laboral]])/7,0),"W")) -> P882W | Z4: =COUNTIF(TablaPercepciones[[#All],[Trabajador]],TablaTrabajadores[[#This Row],[Nombre Trabajador]]) -> 4 | AA4: =COUNTIF(TablaDeducciones[[#All],[Trabajador]],TablaTrabajadores[[#This Row],[Nombre Trabajador]]) -> 1 | AB4: =ROUND(IF((SUMIF(TablaPercepciones[[#All],[Trabajador]],TablaTrabajadores[[#This Row],[Nombre Trabajador]],TablaPercepciones[[#All],[Importe Gravado]]))=0,0,SUMIF(TablaPercepciones[[#All],[Trabajador]],TablaTrabajadores[[#This Row],[Nombre Trabajador]],TablaPercepciones[[#All],[Importe Gravado]])),2) -> #REF! | AC4: =ROUND(IF((SUMIF(TablaPercepciones[[#All],[Trabajador]],TablaTrabajadores[[#This Row],[Nombre Trabajador]],TablaPercepciones[[#All],[o]]))=0,0,SUMIF(TablaPercepciones[[#All],[Trabajador]],TablaTrabajadores[[#This Row],[Nombre Trabajador]],TablaPercepciones[[#All],[o]])),2) -> #REF! | AD4: =ROUND(IF(SUMIFS(TablaDeducciones[[#All],[Importe]],TablaDeducciones[[#All],[Trabajador]],TablaTrabajadores[[#This Row],[Nombre Trabajador]],TablaDeducciones[[#All],[Clave Deducción]],"<>002")=0,0,SUMIFS(TablaDeducciones[[#All],[Importe]],TablaDeducciones[[#All],[Trabajador]],TablaTrabajadores[[#This Row],[Nombre Trabajador]],TablaDeducciones[[#All],[Clave Deducción]],"<>002")),2) -> #REF! | AE4: =ROUND(IF((SUMIFS(TablaDeducciones[[#All],[Importe]],TablaDeducciones[[#All],[Trabajador]],TablaTrabajadores[[#This Row],[Nombre Trabajador]],TablaDeducciones[[#All],[Clave Deducción]],"=002"))=0,0,SUMIFS(TablaDeducciones[[#All],[Importe]],TablaDeducciones[[#All],[Trabajador]],TablaTrabajadores[[#This Row],[Nombre Trabajador]],TablaDeducciones[[#All],[Clave Deducción]],"=002")),2) -> 0 | AF4: =IF(TablaTrabajadores[[#This Row],[Origen del Recurso]]="","",VLOOKUP(TablaTrabajadores[[#This Row],[Origen del Recurso]],Cat!Y:Z,2,0)) -> IP | AG4: =IF(TablaTrabajadores[[#This Row],[Entidad Federativa]]="","",VLOOKUP(TablaTrabajadores[[#This Row],[Entidad Federativa]],Cat!AB:AC,2,0)) -> CHP | AH4: =COUNTIF(TablaHorasExtra[[#All],[Trabajador]],TablaTrabajadores[[#This Row],[Nombre Trabajador]]) -> 0 | AI4: =COUNTIF(TablaOtrosPagos[[#All],[Trabajador]],TablaTrabajadores[[#This Row],[Nombre Trabajador]]) -> 1 | AJ4: =IF(TablaTrabajadores[[#This Row],[Tipo de Jornada]]="","",VLOOKUP(TablaTrabajadores[[#This Row],[Tipo de Jornada]],Cat!AK:AL,2,0)) -> 1 | AK4: =ROUND(IFERROR(SUMIFS(TablaPercepciones[[#All],[Importe Gravado]],TablaPercepciones[[#All],[Trabajador]],TablaTrabajadores[[#This Row],[Nombre Trabajador]],TablaPercepciones[[#All],[Clave Percepción]],"<>022",TablaPercepciones[[#All],[Clave Percepción]],"<>023",TablaPercepciones[[#All],[Clave Percepción]],"<>025",TablaPercepciones[[#All],[Clave Percepción]],"<>044"),0)+IFERROR(SUMIFS(TablaPercepciones[[#All],[o]],TablaPercepciones[[#All],[Trabajador]],TablaTrabajadores[[#This Row],[Nombre Trabajador]],TablaPercepciones[[#All],[Clave Percepción]],"<>022",TablaPercepciones[[#All],[Clave Percepción]],"<>023",TablaPercepciones[[#All],[Clave Percepción]],"<>025",TablaPercepciones[[#All],[Clave Percepción]],"<>044"),0),2) -> 0 | AL4: =ROUND(IFERROR(SUMIFS(TablaPercepciones[[#All],[Importe Gravado]],TablaPercepciones[[#All],[Trabajador]],TablaTrabajadores[[#This Row],[Nombre Trabajador]],TablaPercepciones[[#All],[Clave Percepción]],"=022"),0)+IFERROR(SUMIFS(TablaPercepciones[[#All],[Importe Gravado]],TablaPercepciones[[#All],[Trabajador]],TablaTrabajadores[[#This Row],[Nombre Trabajador]],TablaPercepciones[[#All],[Clave Percepción]],"=023"),0)+IFERROR(SUMIFS(TablaPercepciones[[#All],[Importe Gravado]],TablaPercepciones[[#All],[Trabajador]],TablaTrabajadores[[#This Row],[Nombre Trabajador]],TablaPercepciones[[#All],[Clave Percepción]],"=025"),0)+IFERROR(SUMIFS(TablaPercepciones[[#All],[o]],TablaPercepciones[[#All],[Trabajador]],TablaTrabajadores[[#This Row],[Nombre Trabajador]],TablaPercepciones[[#All],[Clave Percepción]],"=022"),0)+IFERROR(SUMIFS(TablaPercepciones[[#All],[o]],TablaPercepciones[[#All],[Trabajador]],TablaTrabajadores[[#This Row],[Nombre Trabajador]],TablaPercepciones[[#All],[Clave Percepción]],"=023"),0)+IFERROR(SUMIFS(TablaPercepciones[[#All],[o]],TablaPercepciones[[#All],[Trabajador]],TablaTrabajadores[[#This Row],[Nombre Trabajador]],TablaPercepciones[[#All],[Clave Percepción]],"=025"),0),2) -> 0 | AM4: =ROUND(IFERROR(SUMIFS(TablaPercepciones[[#All],[Importe Gravado]],TablaPercepciones[[#All],[Trabajador]],TablaTrabajadores[[#This Row],[Nombre Trabajador]],TablaPercepciones[[#All],[Clave Percepción]],"=039"),0)+IFERROR(SUMIFS(TablaPercepciones[[#All],[Importe Gravado]],TablaPercepciones[[#All],[Trabajador]],TablaTrabajadores[[#This Row],[Nombre Trabajador]],TablaPercepciones[[#All],[Clave Percepción]],"=044"),0)+IFERROR(SUMIFS(TablaPercepciones[[#All],[o]],TablaPercepciones[[#All],[Trabajador]],TablaTrabajadores[[#This Row],[Nombre Trabajador]],TablaPercepciones[[#All],[Clave Percepción]],"=039"),0)+IFERROR(SUMIFS(TablaPercepciones[[#All],[o]],TablaPercepciones[[#All],[Trabajador]],TablaTrabajadores[[#This Row],[Nombre Trabajador]],TablaPercepciones[[#All],[Clave Percepción]],"=044"),0),2) -> 0 | AN4: Diurna
A5: 4 | B5: GOLJ580310TC2 | C5: GOMEZ LOPEZ JUAN | D5: GOLJ580310HCSMPN02 | E5: 71755801777 | F5: 37104 | G5: Contrato de trabajo por tiempo indeterminado | H5: Sueldos | I5: 60 | J5: OFICINA DE PRODUCCION | K5: CONDUCTOR A | L5: 1 | M5: 167.06316 | N5: Ingresos propios | P5: Chiapas | Q5: xuntsima_1@hotmail.com | R5: canal10humanos@gmail.com | T5: =IF(TablaTrabajadores[[#This Row],[Tipo de Contrato]]="","",VLOOKUP(TablaTrabajadores[[#This Row],[Tipo de Contrato]],Cat!$G$1:$H$12,2,0)) -> 1 | U5: =IF(TablaTrabajadores[[#This Row],[Tipo de Régimen]]="","",VLOOKUP(TablaTrabajadores[[#This Row],[Tipo de Régimen]],Cat!$J$1:$K$13,2,0)) -> 2 | V5: =ROUND(IF((SUMIF(TablaPercepciones[[#All],[Trabajador]],TablaTrabajadores[[#This Row],[Nombre Trabajador]],TablaPercepciones[[#All],[Importe Gravado]])+SUMIF(TablaPercepciones[[#All],[Trabajador]],TablaTrabajadores[[#This Row],[Nombre Trabajador]],TablaPercepciones[[#All],[o]]))=0,0,SUMIF(TablaPercepciones[[#All],[Trabajador]],TablaTrabajadores[[#This Row],[Nombre Trabajador]],TablaPercepciones[[#All],[Importe Gravado]])+SUMIF(TablaPercepciones[[#All],[Trabajador]],TablaTrabajadores[[#This Row],[Nombre Trabajador]],TablaPercepciones[[#All],[o]])),2) -> #REF! | W5: =ROUND(IF((SUMIF(TablaDeducciones[[#All],[Trabajador]],TablaTrabajadores[[#This Row],[Nombre Trabajador]],TablaDeducciones[[#All],[Importe]]))=0,0,SUMIF(TablaDeducciones[[#All],[Trabajador]],TablaTrabajadores[[#This Row],[Nombre Trabajador]],TablaDeducciones[[#All],[Importe]])),2) -> #REF! | X5: =ROUND(IF((SUMIF(TablaOtrosPagos[[#All],[Trabajador]],TablaTrabajadores[[#This Row],[Nombre Trabajador]],TablaOtrosPagos[[#All],[Importe]]))=0,0,SUMIF(TablaOtrosPagos[[#All],[Trabajador]],TablaTrabajadores[[#This Row],[Nombre Trabajador]],TablaOtrosPagos[[#All],[Importe]])),2) -> #REF! | Y5: =IF(OR(TablaOrganismo[Fecha Final de pago]="",TablaTrabajadores[[#This Row],[Fecha Inicio Relación Laboral]]=""),"",CONCATENATE("P",ROUNDDOWN((TablaOrganismo[Fecha Final de pago]-TablaTrabajadores[[#This Row],[Fecha Inicio Relación Laboral]])/7,0),"W")) -> P1034W | Z5: =COUNTIF(TablaPercepciones[[#All],[Trabajador]],TablaTrabajadores[[#This Row],[Nombre Trabajador]]) -> 4 | AA5: =COUNTIF(TablaDeducciones[[#All],[Trabajador]],TablaTrabajadores[[#This Row],[Nombre Trabajador]]) -> 1 | AB5: =ROUND(IF((SUMIF(TablaPercepciones[[#All],[Trabajador]],TablaTrabajadores[[#This Row],[Nombre Trabajador]],TablaPercepciones[[#All],[Importe Gravado]]))=0,0,SUMIF(TablaPercepciones[[#All],[Trabajador]],TablaTrabajadores[[#This Row],[Nombre Trabajador]],TablaPercepciones[[#All],[Importe Gravado]])),2) -> #REF! | AC5: =ROUND(IF((SUMIF(TablaPercepciones[[#All],[Trabajador]],TablaTrabajadores[[#This Row],[Nombre Trabajador]],TablaPercepciones[[#All],[o]]))=0,0,SUMIF(TablaPercepciones[[#All],[Trabajador]],TablaTrabajadores[[#This Row],[Nombre Trabajador]],TablaPercepciones[[#All],[o]])),2) -> #REF! | AD5: =ROUND(IF(SUMIFS(TablaDeducciones[[#All],[Importe]],TablaDeducciones[[#All],[Trabajador]],TablaTrabajadores[[#This Row],[Nombre Trabajador]],TablaDeducciones[[#All],[Clave Deducción]],"<>002")=0,0,SUMIFS(TablaDeducciones[[#All],[Importe]],TablaDeducciones[[#All],[Trabajador]],TablaTrabajadores[[#This Row],[Nombre Trabajador]],TablaDeducciones[[#All],[Clave Deducción]],"<>002")),2) -> #REF! | AE5: =ROUND(IF((SUMIFS(TablaDeducciones[[#All],[Importe]],TablaDeducciones[[#All],[Trabajador]],TablaTrabajadores[[#This Row],[Nombre Trabajador]],TablaDeducciones[[#All],[Clave Deducción]],"=002"))=0,0,SUMIFS(TablaDeducciones[[#All],[Importe]],TablaDeducciones[[#All],[Trabajador]],TablaTrabajadores[[#This Row],[Nombre Trabajador]],TablaDeducciones[[#All],[Clave Deducción]],"=002")),2) -> 0 | AF5: =IF(TablaTrabajadores[[#This Row],[Origen del Recurso]]="","",VLOOKUP(TablaTrabajadores[[#This Row],[Origen del Recurso]],Cat!Y:Z,2,0)) -> IP | AG5: =IF(TablaTrabajadores[[#This Row],[Entidad Federativa]]="","",VLOOKUP(TablaTrabajadores[[#This Row],[Entidad Federativa]],Cat!AB:AC,2,0)) -> CHP | AH5: =COUNTIF(TablaHorasExtra[[#All],[Trabajador]],TablaTrabajadores[[#This Row],[Nombre Trabajador]]) -> 0 | AI5: =COUNTIF(TablaOtrosPagos[[#All],[Trabajador]],TablaTrabajadores[[#This Row],[Nombre Trabajador]]) -> 1 | AJ5: =IF(TablaTrabajadores[[#This Row],[Tipo de Jornada]]="","",VLOOKUP(TablaTrabajadores[[#This Row],[Tipo de Jornada]],Cat!AK:AL,2,0)) -> 1 | AK5: =ROUND(IFERROR(SUMIFS(TablaPercepciones[[#All],[Importe Gravado]],TablaPercepciones[[#All],[Trabajador]],TablaTrabajadores[[#This Row],[Nombre Trabajador]],TablaPercepciones[[#All],[Clave Percepción]],"<>022",TablaPercepciones[[#All],[Clave Percepción]],"<>023",TablaPercepciones[[#All],[Clave Percepción]],"<>025",TablaPercepciones[[#All],[Clave Percepción]],"<>044"),0)+IFERROR(SUMIFS(TablaPercepciones[[#All],[o]],TablaPercepciones[[#All],[Trabajador]],TablaTrabajadores[[#This Row],[Nombre Trabajador]],TablaPercepciones[[#All],[Clave Percepción]],"<>022",TablaPercepciones[[#All],[Clave Percepción]],"<>023",TablaPercepciones[[#All],[Clave Percepción]],"<>025",TablaPercepciones[[#All],[Clave Percepción]],"<>044"),0),2) -> 0 | AL5: =ROUND(IFERROR(SUMIFS(TablaPercepciones[[#All],[Importe Gravado]],TablaPercepciones[[#All],[Trabajador]],TablaTrabajadores[[#This Row],[Nombre Trabajador]],TablaPercepciones[[#All],[Clave Percepción]],"=022"),0)+IFERROR(SUMIFS(TablaPercepciones[[#All],[Importe Gravado]],TablaPercepciones[[#All],[Trabajador]],TablaTrabajadores[[#This Row],[Nombre Trabajador]],TablaPercepciones[[#All],[Clave Percepción]],"=023"),0)+IFERROR(SUMIFS(TablaPercepciones[[#All],[Importe Gravado]],TablaPercepciones[[#All],[Trabajador]],TablaTrabajadores[[#This Row],[Nombre Trabajador]],TablaPercepciones[[#All],[Clave Percepción]],"=025"),0)+IFERROR(SUMIFS(TablaPercepciones[[#All],[o]],TablaPercepciones[[#All],[Trabajador]],TablaTrabajadores[[#This Row],[Nombre Trabajador]],TablaPercepciones[[#All],[Clave Percepción]],"=022"),0)+IFERROR(SUMIFS(TablaPercepciones[[#All],[o]],TablaPercepciones[[#All],[Trabajador]],TablaTrabajadores[[#This Row],[Nombre Trabajador]],TablaPercepciones[[#All],[Clave Percepción]],"=023"),0)+IFERROR(SUMIFS(TablaPercepciones[[#All],[o]],TablaPercepciones[[#All],[Trabajador]],TablaTrabajadores[[#This Row],[Nombre Trabajador]],TablaPercepciones[[#All],[Clave Percepción]],"=025"),0),2) -> 0 | AM5: =ROUND(IFERROR(SUMIFS(TablaPercepciones[[#All],[Importe Gravado]],TablaPercepciones[[#All],[Trabajador]],TablaTrabajadores[[#This Row],[Nombre Trabajador]],TablaPercepciones[[#All],[Clave Percepción]],"=039"),0)+IFERROR(SUMIFS(TablaPercepciones[[#All],[Importe Gravado]],TablaPercepciones[[#All],[Trabajador]],TablaTrabajadores[[#This Row],[Nombre Trabajador]],TablaPercepciones[[#All],[Clave Percepción]],"=044"),0)+IFERROR(SUMIFS(TablaPercepciones[[#All],[o]],TablaPercepciones[[#All],[Trabajador]],TablaTrabajadores[[#This Row],[Nombre Trabajador]],TablaPercepciones[[#All],[Clave Percepción]],"=039"),0)+IFERROR(SUMIFS(TablaPercepciones[[#All],[o]],TablaPercepciones[[#All],[Trabajador]],TablaTrabajadores[[#This Row],[Nombre Trabajador]],TablaPercepciones[[#All],[Clave Percepción]],"=044"),0),2) -> 0 | AN5: Diurna
A6: 5 | B6: GOAE930619LGA | C6: GONZALEZ ARCE EDUARDO | D6: GOAE930619HCSNRD05 | E6: 71139306915 | F6: 42902 | G6: Contrato de trabajo por tiempo indeterminado | H6: Sueldos | I6: 986 | J6: DEPARTAMENTO DE PRODUCCION DE NOTICIAS | K6: CHOFER DE APOYO | L6: 1 | M6: 201.81754 | N6: Ingresos propios | P6: Chiapas | Q6: vksip19@gmail.com | R6: canal10humanos@gmail.com | T6: =IF(TablaTrabajadores[[#This Row],[Tipo de Contrato]]="","",VLOOKUP(TablaTrabajadores[[#This Row],[Tipo de Contrato]],Cat!$G$1:$H$12,2,0)) -> 1 | U6: =IF(TablaTrabajadores[[#This Row],[Tipo de Régimen]]="","",VLOOKUP(TablaTrabajadores[[#This Row],[Tipo de Régimen]],Cat!$J$1:$K$13,2,0)) -> 2 | V6: =ROUND(IF((SUMIF(TablaPercepciones[[#All],[Trabajador]],TablaTrabajadores[[#This Row],[Nombre Trabajador]],TablaPercepciones[[#All],[Importe Gravado]])+SUMIF(TablaPercepciones[[#All],[Trabajador]],TablaTrabajadores[[#This Row],[Nombre Trabajador]],TablaPercepciones[[#All],[o]]))=0,0,SUMIF(TablaPercepciones[[#All],[Trabajador]],TablaTrabajadores[[#This Row],[Nombre Trabajador]],TablaPercepciones[[#All],[Importe Gravado]])+SUMIF(TablaPercepciones[[#All],[Trabajador]],TablaTrabajadores[[#This Row],[Nombre Trabajador]],TablaPercepciones[[#All],[o]])),2) -> #REF! | W6: =ROUND(IF((SUMIF(TablaDeducciones[[#All],[Trabajador]],TablaTrabajadores[[#This Row],[Nombre Trabajador]],TablaDeducciones[[#All],[Importe]]))=0,0,SUMIF(TablaDeducciones[[#All],[Trabajador]],TablaTrabajadores[[#This Row],[Nombre Trabajador]],TablaDeducciones[[#All],[Importe]])),2) -> #REF! | X6: =ROUND(IF((SUMIF(TablaOtrosPagos[[#All],[Trabajador]],TablaTrabajadores[[#This Row],[Nombre Trabajador]],TablaOtrosPagos[[#All],[Importe]]))=0,0,SUMIF(TablaOtrosPagos[[#All],[Trabajador]],TablaTrabajadores[[#This Row],[Nombre Trabajador]],TablaOtrosPagos[[#All],[Importe]])),2) -> #REF! | Y6: =IF(OR(TablaOrganismo[Fecha Final de pago]="",TablaTrabajadores[[#This Row],[Fecha Inicio Relación Laboral]]=""),"",CONCATENATE("P",ROUNDDOWN((TablaOrganismo[Fecha Final de pago]-TablaTrabajadores[[#This Row],[Fecha Inicio Relación Laboral]])/7,0),"W")) -> P206W | Z6: =COUNTIF(TablaPercepciones[[#All],[Trabajador]],TablaTrabajadores[[#This Row],[Nombre Trabajador]]) -> 4 | AA6: =COUNTIF(TablaDeducciones[[#All],[Trabajador]],TablaTrabajadores[[#This Row],[Nombre Trabajador]]) -> 2 | AB6: =ROUND(IF((SUMIF(TablaPercepciones[[#All],[Trabajador]],TablaTrabajadores[[#This Row],[Nombre Trabajador]],TablaPercepciones[[#All],[Importe Gravado]]))=0,0,SUMIF(TablaPercepciones[[#All],[Trabajador]],TablaTrabajadores[[#This Row],[Nombre Trabajador]],TablaPercepciones[[#All],[Importe Gravado]])),2) -> #REF! | AC6: =ROUND(IF((SUMIF(TablaPercepciones[[#All],[Trabajador]],TablaTrabajadores[[#This Row],[Nombre Trabajador]],TablaPercepciones[[#All],[o]]))=0,0,SUMIF(TablaPercepciones[[#All],[Trabajador]],TablaTrabajadores[[#This Row],[Nombre Trabajador]],TablaPercepciones[[#All],[o]])),2) -> #REF! | AD6: =ROUND(IF(SUMIFS(TablaDeducciones[[#All],[Importe]],TablaDeducciones[[#All],[Trabajador]],TablaTrabajadores[[#This Row],[Nombre Trabajador]],TablaDeducciones[[#All],[Clave Deducción]],"<>002")=0,0,SUMIFS(TablaDeducciones[[#All],[Importe]],TablaDeducciones[[#All],[Trabajador]],TablaTrabajadores[[#This Row],[Nombre Trabajador]],TablaDeducciones[[#All],[Clave Deducción]],"<>002")),2) -> #REF! | AE6: =ROUND(IF((SUMIFS(TablaDeducciones[[#All],[Importe]],TablaDeducciones[[#All],[Trabajador]],TablaTrabajadores[[#This Row],[Nombre Trabajador]],TablaDeducciones[[#All],[Clave Deducción]],"=002"))=0,0,SUMIFS(TablaDeducciones[[#All],[Importe]],TablaDeducciones[[#All],[Trabajador]],TablaTrabajadores[[#This Row],[Nombre Trabajador]],TablaDeducciones[[#All],[Clave Deducción]],"=002")),2) -> 0 | AF6: =IF(TablaTrabajadores[[#This Row],[Origen del Recurso]]="","",VLOOKUP(TablaTrabajadores[[#This Row],[Origen del Recurso]],Cat!Y:Z,2,0)) -> IP | AG6: =IF(TablaTrabajadores[[#This Row],[Entidad Federativa]]="","",VLOOKUP(TablaTrabajadores[[#This Row],[Entidad Federativa]],Cat!AB:AC,2,0)) -> CHP | AH6: =COUNTIF(TablaHorasExtra[[#All],[Trabajador]],TablaTrabajadores[[#This Row],[Nombre Trabajador]]) -> 0 | AI6: =COUNTIF(TablaOtrosPagos[[#All],[Trabajador]],TablaTrabajadores[[#This Row],[Nombre Trabajador]]) -> 1 | AJ6: =IF(TablaTrabajadores[[#This Row],[Tipo de Jornada]]="","",VLOOKUP(TablaTrabajadores[[#This Row],[Tipo de Jornada]],Cat!AK:AL,2,0)) -> 3 | AK6: =ROUND(IFERROR(SUMIFS(TablaPercepciones[[#All],[Importe Gravado]],TablaPercepciones[[#All],[Trabajador]],TablaTrabajadores[[#This Row],[Nombre Trabajador]],TablaPercepciones[[#All],[Clave Percepción]],"<>022",TablaPercepciones[[#All],[Clave Percepción]],"<>023",TablaPercepciones[[#All],[Clave Percepción]],"<>025",TablaPercepciones[[#All],[Clave Percepción]],"<>044"),0)+IFERROR(SUMIFS(TablaPercepciones[[#All],[o]],TablaPercepciones[[#All],[Trabajador]],TablaTrabajadores[[#This Row],[Nombre Trabajador]],TablaPercepciones[[#All],[Clave Percepción]],"<>022",TablaPercepciones[[#All],[Clave Percepción]],"<>023",TablaPercepciones[[#All],[Clave Percepción]],"<>025",TablaPercepciones[[#All],[Clave Percepción]],"<>044"),0),2) -> 0 | AL6: =ROUND(IFERROR(SUMIFS(TablaPercepciones[[#All],[Importe Gravado]],TablaPercepciones[[#All],[Trabajador]],TablaTrabajadores[[#This Row],[Nombre Trabajador]],TablaPercepciones[[#All],[Clave Percepción]],"=022"),0)+IFERROR(SUMIFS(TablaPercepciones[[#All],[Importe Gravado]],TablaPercepciones[[#All],[Trabajador]],TablaTrabajadores[[#This Row],[Nombre Trabajador]],TablaPercepciones[[#All],[Clave Percepción]],"=023"),0)+IFERROR(SUMIFS(TablaPercepciones[[#All],[Importe Gravado]],TablaPercepciones[[#All],[Trabajador]],TablaTrabajadores[[#This Row],[Nombre Trabajador]],TablaPercepciones[[#All],[Clave Percepción]],"=025"),0)+IFERROR(SUMIFS(TablaPercepciones[[#All],[o]],TablaPercepciones[[#All],[Trabajador]],TablaTrabajadores[[#This Row],[Nombre Trabajador]],TablaPercepciones[[#All],[Clave Percepción]],"=022"),0)+IFERROR(SUMIFS(TablaPercepciones[[#All],[o]],TablaPercepciones[[#All],[Trabajador]],TablaTrabajadores[[#This Row],[Nombre Trabajador]],TablaPercepciones[[#All],[Clave Percepción]],"=023"),0)+IFERROR(SUMIFS(TablaPercepciones[[#All],[o]],TablaPercepciones[[#All],[Trabajador]],TablaTrabajadores[[#This Row],[Nombre Trabajador]],TablaPercepciones[[#All],[Clave Percepción]],"=025"),0),2) -> 0 | AM6: =ROUND(IFERROR(SUMIFS(TablaPercepciones[[#All],[Importe Gravado]],TablaPercepciones[[#All],[Trabajador]],TablaTrabajadores[[#This Row],[Nombre Trabajador]],TablaPercepciones[[#All],[Clave Percepción]],"=039"),0)+IFERROR(SUMIFS(TablaPercepciones[[#All],[Importe Gravado]],TablaPercepciones[[#All],[Trabajador]],TablaTrabajadores[[#This Row],[Nombre Trabajador]],TablaPercepciones[[#All],[Clave Percepción]],"=044"),0)+IFERROR(SUMIFS(TablaPercepciones[[#All],[o]],TablaPercepciones[[#All],[Trabajador]],TablaTrabajadores[[#This Row],[Nombre Trabajador]],TablaPercepciones[[#All],[Clave Percepción]],"=039"),0)+IFERROR(SUMIFS(TablaPercepciones[[#All],[o]],TablaPercepciones[[#All],[Trabajador]],TablaTrabajadores[[#This Row],[Nombre Trabajador]],TablaPercepciones[[#All],[Clave Percepción]],"=044"),0),2) -> 0 | AN6: Mixta
A7: 6 | B7: LEAS8208289V1 | C7: LEEP ARRIAGA SEMEIN AGUSTIN | D7: LEAS820828HCSPRM09 | E7: 71118205427 | F7: 42917 | G7: Contrato de trabajo por tiempo indeterminado | H7: Sueldos | I7: 991 | J7: REPETIDORA TV LACANJA CHANSAYAB XHITC TV | K7: VELADOR | L7: 1 | M7: 157.26603 | N7: Ingresos propios | P7: Chiapas | Q7: gallito_compositor@hotmail.com | R7: canal10humanos@gmail.com | T7: =IF(TablaTrabajadores[[#This Row],[Tipo de Contrato]]="","",VLOOKUP(TablaTrabajadores[[#This Row],[Tipo de Contrato]],Cat!$G$1:$H$12,2,0)) -> 1 | U7: =IF(TablaTrabajadores[[#This Row],[Tipo de Régimen]]="","",VLOOKUP(TablaTrabajadores[[#This Row],[Tipo de Régimen]],Cat!$J$1:$K$13,2,0)) -> 2 | V7: =ROUND(IF((SUMIF(TablaPercepciones[[#All],[Trabajador]],TablaTrabajadores[[#This Row],[Nombre Trabajador]],TablaPercepciones[[#All],[Importe Gravado]])+SUMIF(TablaPercepciones[[#All],[Trabajador]],TablaTrabajadores[[#This Row],[Nombre Trabajador]],TablaPercepciones[[#All],[o]]))=0,0,SUMIF(TablaPercepciones[[#All],[Trabajador]],TablaTrabajadores[[#This Row],[Nombre Trabajador]],TablaPercepciones[[#All],[Importe Gravado]])+SUMIF(TablaPercepciones[[#All],[Trabajador]],TablaTrabajadores[[#This Row],[Nombre Trabajador]],TablaPercepciones[[#All],[o]])),2) -> #REF! | W7: =ROUND(IF((SUMIF(TablaDeducciones[[#All],[Trabajador]],TablaTrabajadores[[#This Row],[Nombre Trabajador]],TablaDeducciones[[#All],[Importe]]))=0,0,SUMIF(TablaDeducciones[[#All],[Trabajador]],TablaTrabajadores[[#This Row],[Nombre Trabajador]],TablaDeducciones[[#All],[Importe]])),2) -> #REF! | X7: =ROUND(IF((SUMIF(TablaOtrosPagos[[#All],[Trabajador]],TablaTrabajadores[[#This Row],[Nombre Trabajador]],TablaOtrosPagos[[#All],[Importe]]))=0,0,SUMIF(TablaOtrosPagos[[#All],[Trabajador]],TablaTrabajadores[[#This Row],[Nombre Trabajador]],TablaOtrosPagos[[#All],[Importe]])),2) -> #REF! | Y7: =IF(OR(TablaOrganismo[Fecha Final de pago]="",TablaTrabajadores[[#This Row],[Fecha Inicio Relación Laboral]]=""),"",CONCATENATE("P",ROUNDDOWN((TablaOrganismo[Fecha Final de pago]-TablaTrabajadores[[#This Row],[Fecha Inicio Relación Laboral]])/7,0),"W")) -> P204W | Z7: =COUNTIF(TablaPercepciones[[#All],[Trabajador]],TablaTrabajadores[[#This Row],[Nombre Trabajador]]) -> 4 | AA7: =COUNTIF(TablaDeducciones[[#All],[Trabajador]],TablaTrabajadores[[#This Row],[Nombre Trabajador]]) -> 1 | AB7: =ROUND(IF((SUMIF(TablaPercepciones[[#All],[Trabajador]],TablaTrabajadores[[#This Row],[Nombre Trabajador]],TablaPercepciones[[#All],[Importe Gravado]]))=0,0,SUMIF(TablaPercepciones[[#All],[Trabajador]],TablaTrabajadores[[#This Row],[Nombre Trabajador]],TablaPercepciones[[#All],[Importe Gravado]])),2) -> #REF! | AC7: =ROUND(IF((SUMIF(TablaPercepciones[[#All],[Trabajador]],TablaTrabajadores[[#This Row],[Nombre Trabajador]],TablaPercepciones[[#All],[o]]))=0,0,SUMIF(TablaPercepciones[[#All],[Trabajador]],TablaTrabajadores[[#This Row],[Nombre Trabajador]],TablaPercepciones[[#All],[o]])),2) -> #REF! | AD7: =ROUND(IF(SUMIFS(TablaDeducciones[[#All],[Importe]],TablaDeducciones[[#All],[Trabajador]],TablaTrabajadores[[#This Row],[Nombre Trabajador]],TablaDeducciones[[#All],[Clave Deducción]],"<>002")=0,0,SUMIFS(TablaDeducciones[[#All],[Importe]],TablaDeducciones[[#All],[Trabajador]],TablaTrabajadores[[#This Row],[Nombre Trabajador]],TablaDeducciones[[#All],[Clave Deducción]],"<>002")),2) -> #REF! | AE7: =ROUND(IF((SUMIFS(TablaDeducciones[[#All],[Importe]],TablaDeducciones[[#All],[Trabajador]],TablaTrabajadores[[#This Row],[Nombre Trabajador]],TablaDeducciones[[#All],[Clave Deducción]],"=002"))=0,0,SUMIFS(TablaDeducciones[[#All],[Importe]],TablaDeducciones[[#All],[Trabajador]],TablaTrabajadores[[#This Row],[Nombre Trabajador]],TablaDeducciones[[#All],[Clave Deducción]],"=002")),2) -> 0 | AF7: =IF(TablaTrabajadores[[#This Row],[Origen del Recurso]]="","",VLOOKUP(TablaTrabajadores[[#This Row],[Origen del Recurso]],Cat!Y:Z,2,0)) -> IP | AG7: =IF(TablaTrabajadores[[#This Row],[Entidad Federativa]]="","",VLOOKUP(TablaTrabajadores[[#This Row],[Entidad Federativa]],Cat!AB:AC,2,0)) -> CHP | AH7: =COUNTIF(TablaHorasExtra[[#All],[Trabajador]],TablaTrabajadores[[#This Row],[Nombre Trabajador]]) -> 0 | AI7: =COUNTIF(TablaOtrosPagos[[#All],[Trabajador]],TablaTrabajadores[[#This Row],[Nombre Trabajador]]) -> 1 | AJ7: =IF(TablaTrabajadores[[#This Row],[Tipo de Jornada]]="","",VLOOKUP(TablaTrabajadores[[#This Row],[Tipo de Jornada]],Cat!AK:AL,2,0)) -> 1 | AK7: =ROUND(IFERROR(SUMIFS(TablaPercepciones[[#All],[Importe Gravado]],TablaPercepciones[[#All],[Trabajador]],TablaTrabajadores[[#This Row],[Nombre Trabajador]],TablaPercepciones[[#All],[Clave Percepción]],"<>022",TablaPercepciones[[#All],[Clave Percepción]],"<>023",TablaPercepciones[[#All],[Clave Percepción]],"<>025",TablaPercepciones[[#All],[Clave Percepción]],"<>044"),0)+IFERROR(SUMIFS(TablaPercepciones[[#All],[o]],TablaPercepciones[[#All],[Trabajador]],TablaTrabajadores[[#This Row],[Nombre Trabajador]],TablaPercepciones[[#All],[Clave Percepción]],"<>022",TablaPercepciones[[#All],[Clave Percepción]],"<>023",TablaPercepciones[[#All],[Clave Percepción]],"<>025",TablaPercepciones[[#All],[Clave Percepción]],"<>044"),0),2) -> 0 | AL7: =ROUND(IFERROR(SUMIFS(TablaPercepciones[[#All],[Importe Gravado]],TablaPercepciones[[#All],[Trabajador]],TablaTrabajadores[[#This Row],[Nombre Trabajador]],TablaPercepciones[[#All],[Clave Percepción]],"=022"),0)+IFERROR(SUMIFS(TablaPercepciones[[#All],[Importe Gravado]],TablaPercepciones[[#All],[Trabajador]],TablaTrabajadores[[#This Row],[Nombre Trabajador]],TablaPercepciones[[#All],[Clave Percepción]],"=023"),0)+IFERROR(SUMIFS(TablaPercepciones[[#All],[Importe Gravado]],TablaPercepciones[[#All],[Trabajador]],TablaTrabajadores[[#This Row],[Nombre Trabajador]],TablaPercepciones[[#All],[Clave Percepción]],"=025"),0)+IFERROR(SUMIFS(TablaPercepciones[[#All],[o]],TablaPercepciones[[#All],[Trabajador]],TablaTrabajadores[[#This Row],[Nombre Trabajador]],TablaPercepciones[[#All],[Clave Percepción]],"=022"),0)+IFERROR(SUMIFS(TablaPercepciones[[#All],[o]],TablaPercepciones[[#All],[Trabajador]],TablaTrabajadores[[#This Row],[Nombre Trabajador]],TablaPercepciones[[#All],[Clave Percepción]],"=023"),0)+IFERROR(SUMIFS(TablaPercepciones[[#All],[o]],TablaPercepciones[[#All],[Trabajador]],TablaTrabajadores[[#This Row],[Nombre Trabajador]],TablaPercepciones[[#All],[Clave Percepción]],"=025"),0),2) -> 0 | AM7: =ROUND(IFERROR(SUMIFS(TablaPercepciones[[#All],[Importe Gravado]],TablaPercepciones[[#All],[Trabajador]],TablaTrabajadores[[#This Row],[Nombre Trabajador]],TablaPercepciones[[#All],[Clave Percepción]],"=039"),0)+IFERROR(SUMIFS(TablaPercepciones[[#All],[Importe Gravado]],TablaPercepciones[[#All],[Trabajador]],TablaTrabajadores[[#This Row],[Nombre Trabajador]],TablaPercepciones[[#All],[Clave Percepción]],"=044"),0)+IFERROR(SUMIFS(TablaPercepciones[[#All],[o]],TablaPercepciones[[#All],[Trabajador]],TablaTrabajadores[[#This Row],[Nombre Trabajador]],TablaPercepciones[[#All],[Clave Percepción]],"=039"),0)+IFERROR(SUMIFS(TablaPercepciones[[#All],[o]],TablaPercepciones[[#All],[Trabajador]],TablaTrabajadores[[#This Row],[Nombre Trabajador]],TablaPercepciones[[#All],[Clave Percepción]],"=044"),0),2) -> 0 | AN7: Diurna
A8: 7 | B8: LOML860415SN4 | C8: LOPEZ MENDEZ LETICIA GUADALUPE | D8: LOML860415MCSPNT05 | E8: 71128617330 | F8: 43647 | G8: Contrato de trabajo por tiempo indeterminado | H8: Sueldos | I8: 5170 | J8: GERENCIA DE RADIO XHCTN LA TRINITARIA | K8: VELADOR | L8: 1 | M8: 157.26603 | N8: Ingresos propios | P8: Chiapas | Q8: joluma122@hotmail.com | R8: canal10humanos@gmail.com | T8: =IF(TablaTrabajadores[[#This Row],[Tipo de Contrato]]="","",VLOOKUP(TablaTrabajadores[[#This Row],[Tipo de Contrato]],Cat!$G$1:$H$12,2,0)) -> 1 | U8: =IF(TablaTrabajadores[[#This Row],[Tipo de Régimen]]="","",VLOOKUP(TablaTrabajadores[[#This Row],[Tipo de Régimen]],Cat!$J$1:$K$13,2,0)) -> 2 | V8: =ROUND(IF((SUMIF(TablaPercepciones[[#All],[Trabajador]],TablaTrabajadores[[#This Row],[Nombre Trabajador]],TablaPercepciones[[#All],[Importe Gravado]])+SUMIF(TablaPercepciones[[#All],[Trabajador]],TablaTrabajadores[[#This Row],[Nombre Trabajador]],TablaPercepciones[[#All],[o]]))=0,0,SUMIF(TablaPercepciones[[#All],[Trabajador]],TablaTrabajadores[[#This Row],[Nombre Trabajador]],TablaPercepciones[[#All],[Importe Gravado]])+SUMIF(TablaPercepciones[[#All],[Trabajador]],TablaTrabajadores[[#This Row],[Nombre Trabajador]],TablaPercepciones[[#All],[o]])),2) -> #REF! | W8: =ROUND(IF((SUMIF(TablaDeducciones[[#All],[Trabajador]],TablaTrabajadores[[#This Row],[Nombre Trabajador]],TablaDeducciones[[#All],[Importe]]))=0,0,SUMIF(TablaDeducciones[[#All],[Trabajador]],TablaTrabajadores[[#This Row],[Nombre Trabajador]],TablaDeducciones[[#All],[Importe]])),2) -> #REF! | X8: =ROUND(IF((SUMIF(TablaOtrosPagos[[#All],[Trabajador]],TablaTrabajadores[[#This Row],[Nombre Trabajador]],TablaOtrosPagos[[#All],[Importe]]))=0,0,SUMIF(TablaOtrosPagos[[#All],[Trabajador]],TablaTrabajadores[[#This Row],[Nombre Trabajador]],TablaOtrosPagos[[#All],[Importe]])),2) -> #REF! | Y8: =IF(OR(TablaOrganismo[Fecha Final de pago]="",TablaTrabajadores[[#This Row],[Fecha Inicio Relación Laboral]]=""),"",CONCATENATE("P",ROUNDDOWN((TablaOrganismo[Fecha Final de pago]-TablaTrabajadores[[#This Row],[Fecha Inicio Relación Laboral]])/7,0),"W")) -> P100W | Z8: =COUNTIF(TablaPercepciones[[#All],[Trabajador]],TablaTrabajadores[[#This Row],[Nombre Trabajador]]) -> 4 | AA8: =COUNTIF(TablaDeducciones[[#All],[Trabajador]],TablaTrabajadores[[#This Row],[Nombre Trabajador]]) -> 1 | AB8: =ROUND(IF((SUMIF(TablaPercepciones[[#All],[Trabajador]],TablaTrabajadores[[#This Row],[Nombre Trabajador]],TablaPercepciones[[#All],[Importe Gravado]]))=0,0,SUMIF(TablaPercepciones[[#All],[Trabajador]],TablaTrabajadores[[#This Row],[Nombre Trabajador]],TablaPercepciones[[#All],[Importe Gravado]])),2) -> #REF! | AC8: =ROUND(IF((SUMIF(TablaPercepciones[[#All],[Trabajador]],TablaTrabajadores[[#This Row],[Nombre Trabajador]],TablaPercepciones[[#All],[o]]))=0,0,SUMIF(TablaPercepciones[[#All],[Trabajador]],TablaTrabajadores[[#This Row],[Nombre Trabajador]],TablaPercepciones[[#All],[o]])),2) -> #REF! | AD8: =ROUND(IF(SUMIFS(TablaDeducciones[[#All],[Importe]],TablaDeducciones[[#All],[Trabajador]],TablaTrabajadores[[#This Row],[Nombre Trabajador]],TablaDeducciones[[#All],[Clave Deducción]],"<>002")=0,0,SUMIFS(TablaDeducciones[[#All],[Importe]],TablaDeducciones[[#All],[Trabajador]],TablaTrabajadores[[#This Row],[Nombre Trabajador]],TablaDeducciones[[#All],[Clave Deducción]],"<>002")),2) -> #REF! | AE8: =ROUND(IF((SUMIFS(TablaDeducciones[[#All],[Importe]],TablaDeducciones[[#All],[Trabajador]],TablaTrabajadores[[#This Row],[Nombre Trabajador]],TablaDeducciones[[#All],[Clave Deducción]],"=002"))=0,0,SUMIFS(TablaDeducciones[[#All],[Importe]],TablaDeducciones[[#All],[Trabajador]],TablaTrabajadores[[#This Row],[Nombre Trabajador]],TablaDeducciones[[#All],[Clave Deducción]],"=002")),2) -> 0 | AF8: =IF(TablaTrabajadores[[#This Row],[Origen del Recurso]]="","",VLOOKUP(TablaTrabajadores[[#This Row],[Origen del Recurso]],Cat!Y:Z,2,0)) -> IP | AG8: =IF(TablaTrabajadores[[#This Row],[Entidad Federativa]]="","",VLOOKUP(TablaTrabajadores[[#This Row],[Entidad Federativa]],Cat!AB:AC,2,0)) -> CHP | AH8: =COUNTIF(TablaHorasExtra[[#All],[Trabajador]],TablaTrabajadores[[#This Row],[Nombre Trabajador]]) -> 0 | AI8: =COUNTIF(TablaOtrosPagos[[#All],[Trabajador]],TablaTrabajadores[[#This Row],[Nombre Trabajador]]) -> 1 | AJ8: =IF(TablaTrabajadores[[#This Row],[Tipo de Jornada]]="","",VLOOKUP(TablaTrabajadores[[#This Row],[Tipo de Jornada]],Cat!AK:AL,2,0)) -> 3 | AK8: =ROUND(IFERROR(SUMIFS(TablaPercepciones[[#All],[Importe Gravado]],TablaPercepciones[[#All],[Trabajador]],TablaTrabajadores[[#This Row],[Nombre Trabajador]],TablaPercepciones[[#All],[Clave Percepción]],"<>022",TablaPercepciones[[#All],[Clave Percepción]],"<>023",TablaPercepciones[[#All],[Clave Percepción]],"<>025",TablaPercepciones[[#All],[Clave Percepción]],"<>044"),0)+IFERROR(SUMIFS(TablaPercepciones[[#All],[o]],TablaPercepciones[[#All],[Trabajador]],TablaTrabajadores[[#This Row],[Nombre Trabajador]],TablaPercepciones[[#All],[Clave Percepción]],"<>022",TablaPercepciones[[#All],[Clave Percepción]],"<>023",TablaPercepciones[[#All],[Clave Percepción]],"<>025",TablaPercepciones[[#All],[Clave Percepción]],"<>044"),0),2) -> 0 | AL8: =ROUND(IFERROR(SUMIFS(TablaPercepciones[[#All],[Importe Gravado]],TablaPercepciones[[#All],[Trabajador]],TablaTrabajadores[[#This Row],[Nombre Trabajador]],TablaPercepciones[[#All],[Clave Percepción]],"=022"),0)+IFERROR(SUMIFS(TablaPercepciones[[#All],[Importe Gravado]],TablaPercepciones[[#All],[Trabajador]],TablaTrabajadores[[#This Row],[Nombre Trabajador]],TablaPercepciones[[#All],[Clave Percepción]],"=023"),0)+IFERROR(SUMIFS(TablaPercepciones[[#All],[Importe Gravado]],TablaPercepciones[[#All],[Trabajador]],TablaTrabajadores[[#This Row],[Nombre Trabajador]],TablaPercepciones[[#All],[Clave Percepción]],"=025"),0)+IFERROR(SUMIFS(TablaPercepciones[[#All],[o]],TablaPercepciones[[#All],[Trabajador]],TablaTrabajadores[[#This Row],[Nombre Trabajador]],TablaPercepciones[[#All],[Clave Percepción]],"=022"),0)+IFERROR(SUMIFS(TablaPercepciones[[#All],[o]],TablaPercepciones[[#All],[Trabajador]],TablaTrabajadores[[#This Row],[Nombre Trabajador]],TablaPercepciones[[#All],[Clave Percepción]],"=023"),0)+IFERROR(SUMIFS(TablaPercepciones[[#All],[o]],TablaPercepciones[[#All],[Trabajador]],TablaTrabajadores[[#This Row],[Nombre Trabajador]],TablaPercepciones[[#All],[Clave Percepción]],"=025"),0),2) -> 0 | AM8: =ROUND(IFERROR(SUMIFS(TablaPercepciones[[#All],[Importe Gravado]],TablaPercepciones[[#All],[Trabajador]],TablaTrabajadores[[#This Row],[Nombre Trabajador]],TablaPercepciones[[#All],[Clave Percepción]],"=039"),0)+IFERROR(SUMIFS(TablaPercepciones[[#All],[Importe Gravado]],TablaPercepciones[[#All],[Trabajador]],TablaTrabajadores[[#This Row],[Nombre Trabajador]],TablaPercepciones[[#All],[Clave Percepción]],"=044"),0)+IFERROR(SUMIFS(TablaPercepciones[[#All],[o]],TablaPercepciones[[#All],[Trabajador]],TablaTrabajadores[[#This Row],[Nombre Trabajador]],TablaPercepciones[[#All],[Clave Percepción]],"=039"),0)+IFERROR(SUMIFS(TablaPercepciones[[#All],[o]],TablaPercepciones[[#All],[Trabajador]],TablaTrabajadores[[#This Row],[Nombre Trabajador]],TablaPercepciones[[#All],[Clave Percepción]],"=044"),0),2) -> 0 | AN8: Mixta
A9: 8 | B9: LOOL710327L22 | C9: LOPEZ OVANDO LEANDRA GUADALUPE | D9: LOOL710327MCSPVN04 | E9: 71917147556 | F9: 43116 | G9: Contrato de trabajo por tiempo indeterminado | H9: Sueldos | I9: 5126 | J9: OFICINA DE PRODUCCION | K9: CONDUCTOR A | L9: 1 | M9: 166.5397 | N9: Ingresos propios | P9: Chiapas | Q9: grupera29103@hotmail.com | R9: canal10humanos@gmail.com | T9: =IF(TablaTrabajadores[[#This Row],[Tipo de Contrato]]="","",VLOOKUP(TablaTrabajadores[[#This Row],[Tipo de Contrato]],Cat!$G$1:$H$12,2,0)) -> 1 | U9: =IF(TablaTrabajadores[[#This Row],[Tipo de Régimen]]="","",VLOOKUP(TablaTrabajadores[[#This Row],[Tipo de Régimen]],Cat!$J$1:$K$13,2,0)) -> 2 | V9: =ROUND(IF((SUMIF(TablaPercepciones[[#All],[Trabajador]],TablaTrabajadores[[#This Row],[Nombre Trabajador]],TablaPercepciones[[#All],[Importe Gravado]])+SUMIF(TablaPercepciones[[#All],[Trabajador]],TablaTrabajadores[[#This Row],[Nombre Trabajador]],TablaPercepciones[[#All],[o]]))=0,0,SUMIF(TablaPercepciones[[#All],[Trabajador]],TablaTrabajadores[[#This Row],[Nombre Trabajador]],TablaPercepciones[[#All],[Importe Gravado]])+SUMIF(TablaPercepciones[[#All],[Trabajador]],TablaTrabajadores[[#This Row],[Nombre Trabajador]],TablaPercepciones[[#All],[o]])),2) -> #REF! | W9: =ROUND(IF((SUMIF(TablaDeducciones[[#All],[Trabajador]],TablaTrabajadores[[#This Row],[Nombre Trabajador]],TablaDeducciones[[#All],[Importe]]))=0,0,SUMIF(TablaDeducciones[[#All],[Trabajador]],TablaTrabajadores[[#This Row],[Nombre Trabajador]],TablaDeducciones[[#All],[Importe]])),2) -> #REF! | X9: =ROUND(IF((SUMIF(TablaOtrosPagos[[#All],[Trabajador]],TablaTrabajadores[[#This Row],[Nombre Trabajador]],TablaOtrosPagos[[#All],[Importe]]))=0,0,SUMIF(TablaOtrosPagos[[#All],[Trabajador]],TablaTrabajadores[[#This Row],[Nombre Trabajador]],TablaOtrosPagos[[#All],[Importe]])),2) -> #REF! | Y9: =IF(OR(TablaOrganismo[Fecha Final de pago]="",TablaTrabajadores[[#This Row],[Fecha Inicio Relación Laboral]]=""),"",CONCATENATE("P",ROUNDDOWN((TablaOrganismo[Fecha Final de pago]-TablaTrabajadores[[#This Row],[Fecha Inicio Relación Laboral]])/7,0),"W")) -> P175W | Z9: =COUNTIF(TablaPercepciones[[#All],[Trabajador]],TablaTrabajadores[[#This Row],[Nombre Trabajador]]) -> 4 | AA9: =COUNTIF(TablaDeducciones[[#All],[Trabajador]],TablaTrabajadores[[#This Row],[Nombre Trabajador]]) -> 3 | AB9: =ROUND(IF((SUMIF(TablaPercepciones[[#All],[Trabajador]],TablaTrabajadores[[#This Row],[Nombre Trabajador]],TablaPercepciones[[#All],[Importe Gravado]]))=0,0,SUMIF(TablaPercepciones[[#All],[Trabajador]],TablaTrabajadores[[#This Row],[Nombre Trabajador]],TablaPercepciones[[#All],[Importe Gravado]])),2) -> #REF! | AC9: =ROUND(IF((SUMIF(TablaPercepciones[[#All],[Trabajador]],TablaTrabajadores[[#This Row],[Nombre Trabajador]],TablaPercepciones[[#All],[o]]))=0,0,SUMIF(TablaPercepciones[[#All],[Trabajador]],TablaTrabajadores[[#This Row],[Nombre Trabajador]],TablaPercepciones[[#All],[o]])),2) -> #REF! | AD9: =ROUND(IF(SUMIFS(TablaDeducciones[[#All],[Importe]],TablaDeducciones[[#All],[Trabajador]],TablaTrabajadores[[#This Row],[Nombre Trabajador]],TablaDeducciones[[#All],[Clave Deducción]],"<>002")=0,0,SUMIFS(TablaDeducciones[[#All],[Importe]],TablaDeducciones[[#All],[Trabajador]],TablaTrabajadores[[#This Row],[Nombre Trabajador]],TablaDeducciones[[#All],[Clave Deducción]],"<>002")),2) -> #REF! | AE9: =ROUND(IF((SUMIFS(TablaDeducciones[[#All],[Importe]],TablaDeducciones[[#All],[Trabajador]],TablaTrabajadores[[#This Row],[Nombre Trabajador]],TablaDeducciones[[#All],[Clave Deducción]],"=002"))=0,0,SUMIFS(TablaDeducciones[[#All],[Importe]],TablaDeducciones[[#All],[Trabajador]],TablaTrabajadores[[#This Row],[Nombre Trabajador]],TablaDeducciones[[#All],[Clave Deducción]],"=002")),2) -> 0 | AF9: =IF(TablaTrabajadores[[#This Row],[Origen del Recurso]]="","",VLOOKUP(TablaTrabajadores[[#This Row],[Origen del Recurso]],Cat!Y:Z,2,0)) -> IP | AG9: =IF(TablaTrabajadores[[#This Row],[Entidad Federativa]]="","",VLOOKUP(TablaTrabajadores[[#This Row],[Entidad Federativa]],Cat!AB:AC,2,0)) -> CHP | AH9: =COUNTIF(TablaHorasExtra[[#All],[Trabajador]],TablaTrabajadores[[#This Row],[Nombre Trabajador]]) -> 0 | AI9: =COUNTIF(TablaOtrosPagos[[#All],[Trabajador]],TablaTrabajadores[[#This Row],[Nombre Trabajador]]) -> 1 | AJ9: =IF(TablaTrabajadores[[#This Row],[Tipo de Jornada]]="","",VLOOKUP(TablaTrabajadores[[#This Row],[Tipo de Jornada]],Cat!AK:AL,2,0)) -> 1 | AK9: =ROUND(IFERROR(SUMIFS(TablaPercepciones[[#All],[Importe Gravado]],TablaPercepciones[[#All],[Trabajador]],TablaTrabajadores[[#This Row],[Nombre Trabajador]],TablaPercepciones[[#All],[Clave Percepción]],"<>022",TablaPercepciones[[#All],[Clave Percepción]],"<>023",TablaPercepciones[[#All],[Clave Percepción]],"<>025",TablaPercepciones[[#All],[Clave Percepción]],"<>044"),0)+IFERROR(SUMIFS(TablaPercepciones[[#All],[o]],TablaPercepciones[[#All],[Trabajador]],TablaTrabajadores[[#This Row],[Nombre Trabajador]],TablaPercepciones[[#All],[Clave Percepción]],"<>022",TablaPercepciones[[#All],[Clave Percepción]],"<>023",TablaPercepciones[[#All],[Clave Percepción]],"<>025",TablaPercepciones[[#All],[Clave Percepción]],"<>044"),0),2) -> 0 | AL9: =ROUND(IFERROR(SUMIFS(TablaPercepciones[[#All],[Importe Gravado]],TablaPercepciones[[#All],[Trabajador]],TablaTrabajadores[[#This Row],[Nombre Trabajador]],TablaPercepciones[[#All],[Clave Percepción]],"=022"),0)+IFERROR(SUMIFS(TablaPercepciones[[#All],[Importe Gravado]],TablaPercepciones[[#All],[Trabajador]],TablaTrabajadores[[#This Row],[Nombre Trabajador]],TablaPercepciones[[#All],[Clave Percepción]],"=023"),0)+IFERROR(SUMIFS(TablaPercepciones[[#All],[Importe Gravado]],TablaPercepciones[[#All],[Trabajador]],TablaTrabajadores[[#This Row],[Nombre Trabajador]],TablaPercepciones[[#All],[Clave Percepción]],"=025"),0)+IFERROR(SUMIFS(TablaPercepciones[[#All],[o]],TablaPercepciones[[#All],[Trabajador]],TablaTrabajadores[[#This Row],[Nombre Trabajador]],TablaPercepciones[[#All],[Clave Percepción]],"=022"),0)+IFERROR(SUMIFS(TablaPercepciones[[#All],[o]],TablaPercepciones[[#All],[Trabajador]],TablaTrabajadores[[#This Row],[Nombre Trabajador]],TablaPercepciones[[#All],[Clave Percepción]],"=023"),0)+IFERROR(SUMIFS(TablaPercepciones[[#All],[o]],TablaPercepciones[[#All],[Trabajador]],TablaTrabajadores[[#This Row],[Nombre Trabajador]],TablaPercepciones[[#All],[Clave Percepción]],"=025"),0),2) -> 0 | AM9: =ROUND(IFERROR(SUMIFS(TablaPercepciones[[#All],[Importe Gravado]],TablaPercepciones[[#All],[Trabajador]],TablaTrabajadores[[#This Row],[Nombre Trabajador]],TablaPercepciones[[#All],[Clave Percepción]],"=039"),0)+IFERROR(SUMIFS(TablaPercepciones[[#All],[Importe Gravado]],TablaPercepciones[[#All],[Trabajador]],TablaTrabajadores[[#This Row],[Nombre Trabajador]],TablaPercepciones[[#All],[Clave Percepción]],"=044"),0)+IFERROR(SUMIFS(TablaPercepciones[[#All],[o]],TablaPercepciones[[#All],[Trabajador]],TablaTrabajadores[[#This Row],[Nombre Trabajador]],TablaPercepciones[[#All],[Clave Percepción]],"=039"),0)+IFERROR(SUMIFS(TablaPercepciones[[#All],[o]],TablaPercepciones[[#All],[Trabajador]],TablaTrabajadores[[#This Row],[Nombre Trabajador]],TablaPercepciones[[#All],[Clave Percepción]],"=044"),0),2) -> 0 | AN9: Diurna
A10: 9 | B10: MESM740315GK2 | C10: MENDEZ SANCHEZ MIGUEL | D10: MESM740315HCSNNG05 | E10: 71087402260 | F10: 39569 | G10: Contrato de trabajo por tiempo indeterminado | H10: Sueldos | I10: 362 | J10: GERENCIA DE RADIO XHSDM SANTO DOMINGO | K10: VELADOR | L10: 1 | M10: 157.76034 | N10: Ingresos propios | P10: Chiapas | Q10: xhsdmmiguel@gmail.com | R10: canal10humanos@gmail.com | T10: =IF(TablaTrabajadores[[#This Row],[Tipo de Contrato]]="","",VLOOKUP(TablaTrabajadores[[#This Row],[Tipo de Contrato]],Cat!$G$1:$H$12,2,0)) -> 1 | U10: =IF(TablaTrabajadores[[#This Row],[Tipo de Régimen]]="","",VLOOKUP(TablaTrabajadores[[#This Row],[Tipo de Régimen]],Cat!$J$1:$K$13,2,0)) -> 2 | V10: =ROUND(IF((SUMIF(TablaPercepciones[[#All],[Trabajador]],TablaTrabajadores[[#This Row],[Nombre Trabajador]],TablaPercepciones[[#All],[Importe Gravado]])+SUMIF(TablaPercepciones[[#All],[Trabajador]],TablaTrabajadores[[#This Row],[Nombre Trabajador]],TablaPercepciones[[#All],[o]]))=0,0,SUMIF(TablaPercepciones[[#All],[Trabajador]],TablaTrabajadores[[#This Row],[Nombre Trabajador]],TablaPercepciones[[#All],[Importe Gravado]])+SUMIF(TablaPercepciones[[#All],[Trabajador]],TablaTrabajadores[[#This Row],[Nombre Trabajador]],TablaPercepciones[[#All],[o]])),2) -> #REF! | W10: =ROUND(IF((SUMIF(TablaDeducciones[[#All],[Trabajador]],TablaTrabajadores[[#This Row],[Nombre Trabajador]],TablaDeducciones[[#All],[Importe]]))=0,0,SUMIF(TablaDeducciones[[#All],[Trabajador]],TablaTrabajadores[[#This Row],[Nombre Trabajador]],TablaDeducciones[[#All],[Importe]])),2) -> #REF! | X10: =ROUND(IF((SUMIF(TablaOtrosPagos[[#All],[Trabajador]],TablaTrabajadores[[#This Row],[Nombre Trabajador]],TablaOtrosPagos[[#All],[Importe]]))=0,0,SUMIF(TablaOtrosPagos[[#All],[Trabajador]],TablaTrabajadores[[#This Row],[Nombre Trabajador]],TablaOtrosPagos[[#All],[Importe]])),2) -> #REF! | Y10: =IF(OR(TablaOrganismo[Fecha Final de pago]="",TablaTrabajadores[[#This Row],[Fecha Inicio Relación Laboral]]=""),"",CONCATENATE("P",ROUNDDOWN((TablaOrganismo[Fecha Final de pago]-TablaTrabajadores[[#This Row],[Fecha Inicio Relación Laboral]])/7,0),"W")) -> P682W | Z10: =COUNTIF(TablaPercepciones[[#All],[Trabajador]],TablaTrabajadores[[#This Row],[Nombre Trabajador]]) -> 4 | AA10: =COUNTIF(TablaDeducciones[[#All],[Trabajador]],TablaTrabajadores[[#This Row],[Nombre Trabajador]]) -> 1 | AB10: =ROUND(IF((SUMIF(TablaPercepciones[[#All],[Trabajador]],TablaTrabajadores[[#This Row],[Nombre Trabajador]],TablaPercepciones[[#All],[Importe Gravado]]))=0,0,SUMIF(TablaPercepciones[[#All],[Trabajador]],TablaTrabajadores[[#This Row],[Nombre Trabajador]],TablaPercepciones[[#All],[Importe Gravado]])),2) -> #REF! | AC10: =ROUND(IF((SUMIF(TablaPercepciones[[#All],[Trabajador]],TablaTrabajadores[[#This Row],[Nombre Trabajador]],TablaPercepciones[[#All],[o]]))=0,0,SUMIF(TablaPercepciones[[#All],[Trabajador]],TablaTrabajadores[[#This Row],[Nombre Trabajador]],TablaPercepciones[[#All],[o]])),2) -> #REF! | AD10: =ROUND(IF(SUMIFS(TablaDeducciones[[#All],[Importe]],TablaDeducciones[[#All],[Trabajador]],TablaTrabajadores[[#This Row],[Nombre Trabajador]],TablaDeducciones[[#All],[Clave Deducción]],"<>002")=0,0,SUMIFS(TablaDeducciones[[#All],[Importe]],TablaDeducciones[[#All],[Trabajador]],TablaTrabajadores[[#This Row],[Nombre Trabajador]],TablaDeducciones[[#All],[Clave Deducción]],"<>002")),2) -> #REF! | AE10: =ROUND(IF((SUMIFS(TablaDeducciones[[#All],[Importe]],TablaDeducciones[[#All],[Trabajador]],TablaTrabajadores[[#This Row],[Nombre Trabajador]],TablaDeducciones[[#All],[Clave Deducción]],"=002"))=0,0,SUMIFS(TablaDeducciones[[#All],[Importe]],TablaDeducciones[[#All],[Trabajador]],TablaTrabajadores[[#This Row],[Nombre Trabajador]],TablaDeducciones[[#All],[Clave Deducción]],"=002")),2) -> 0 | AF10: =IF(TablaTrabajadores[[#This Row],[Origen del Recurso]]="","",VLOOKUP(TablaTrabajadores[[#This Row],[Origen del Recurso]],Cat!Y:Z,2,0)) -> IP | AG10: =IF(TablaTrabajadores[[#This Row],[Entidad Federativa]]="","",VLOOKUP(TablaTrabajadores[[#This Row],[Entidad Federativa]],Cat!AB:AC,2,0)) -> CHP | AH10: =COUNTIF(TablaHorasExtra[[#All],[Trabajador]],TablaTrabajadores[[#This Row],[Nombre Trabajador]]) -> 0 | AI10: =COUNTIF(TablaOtrosPagos[[#All],[Trabajador]],TablaTrabajadores[[#This Row],[Nombre Trabajador]]) -> 1 | AJ10: =IF(TablaTrabajadores[[#This Row],[Tipo de Jornada]]="","",VLOOKUP(TablaTrabajadores[[#This Row],[Tipo de Jornada]],Cat!AK:AL,2,0)) -> 2 | AK10: =ROUND(IFERROR(SUMIFS(TablaPercepciones[[#All],[Importe Gravado]],TablaPercepciones[[#All],[Trabajador]],TablaTrabajadores[[#This Row],[Nombre Trabajador]],TablaPercepciones[[#All],[Clave Percepción]],"<>022",TablaPercepciones[[#All],[Clave Percepción]],"<>023",TablaPercepciones[[#All],[Clave Percepción]],"<>025",TablaPercepciones[[#All],[Clave Percepción]],"<>044"),0)+IFERROR(SUMIFS(TablaPercepciones[[#All],[o]],TablaPercepciones[[#All],[Trabajador]],TablaTrabajadores[[#This Row],[Nombre Trabajador]],TablaPercepciones[[#All],[Clave Percepción]],"<>022",TablaPercepciones[[#All],[Clave Percepción]],"<>023",TablaPercepciones[[#All],[Clave Percepción]],"<>025",TablaPercepciones[[#All],[Clave Percepción]],"<>044"),0),2) -> 0 | AL10: =ROUND(IFERROR(SUMIFS(TablaPercepciones[[#All],[Importe Gravado]],TablaPercepciones[[#All],[Trabajador]],TablaTrabajadores[[#This Row],[Nombre Trabajador]],TablaPercepciones[[#All],[Clave Percepción]],"=022"),0)+IFERROR(SUMIFS(TablaPercepciones[[#All],[Importe Gravado]],TablaPercepciones[[#All],[Trabajador]],TablaTrabajadores[[#This Row],[Nombre Trabajador]],TablaPercepciones[[#All],[Clave Percepción]],"=023"),0)+IFERROR(SUMIFS(TablaPercepciones[[#All],[Importe Gravado]],TablaPercepciones[[#All],[Trabajador]],TablaTrabajadores[[#This Row],[Nombre Trabajador]],TablaPercepciones[[#All],[Clave Percepción]],"=025"),0)+IFERROR(SUMIFS(TablaPercepciones[[#All],[o]],TablaPercepciones[[#All],[Trabajador]],TablaTrabajadores[[#This Row],[Nombre Trabajador]],TablaPercepciones[[#All],[Clave Percepción]],"=022"),0)+IFERROR(SUMIFS(TablaPercepciones[[#All],[o]],TablaPercepciones[[#All],[Trabajador]],TablaTrabajadores[[#This Row],[Nombre Trabajador]],TablaPercepciones[[#All],[Clave Percepción]],"=023"),0)+IFERROR(SUMIFS(TablaPercepciones[[#All],[o]],TablaPercepciones[[#All],[Trabajador]],TablaTrabajadores[[#This Row],[Nombre Trabajador]],TablaPercepciones[[#All],[Clave Percepción]],"=025"),0),2) -> 0 | AM10: =ROUND(IFERROR(SUMIFS(TablaPercepciones[[#All],[Importe Gravado]],TablaPercepciones[[#All],[Trabajador]],TablaTrabajadores[[#This Row],[Nombre Trabajador]],TablaPercepciones[[#All],[Clave Percepción]],"=039"),0)+IFERROR(SUMIFS(TablaPercepciones[[#All],[Importe Gravado]],TablaPercepciones[[#All],[Trabajador]],TablaTrabajadores[[#This Row],[Nombre Trabajador]],TablaPercepciones[[#All],[Clave Percepción]],"=044"),0)+IFERROR(SUMIFS(TablaPercepciones[[#All],[o]],TablaPercepciones[[#All],[Trabajador]],TablaTrabajadores[[#This Row],[Nombre Trabajador]],TablaPercepciones[[#All],[Clave Percepción]],"=039"),0)+IFERROR(SUMIFS(TablaPercepciones[[#All],[o]],TablaPercepciones[[#All],[Trabajador]],TablaTrabajadores[[#This Row],[Nombre Trabajador]],TablaPercepciones[[#All],[Clave Percepción]],"=044"),0),2) -> 0 | AN10: Nocturna
A11: 10 | B11: NANG600509D50 | C11: NAJERA NAJERA GREGORIO CESAR | D11: NANG600509HCSJJR09 | E11: 71796009505 | F11: 43497 | G11: Contrato de trabajo por tiempo indeterminado | H11: Sueldos | I11: 5140 | J11: AREA DE RECURSOS MATERIALES | K11: VELADOR | L11: 1 | M11: 157.26603 | N11: Ingresos propios | P11: Chiapas | Q11: canal10humanos@gmail.com | R11: canal10humanos@gmail.com | T11: =IF(TablaTrabajadores[[#This Row],[Tipo de Contrato]]="","",VLOOKUP(TablaTrabajadores[[#This Row],[Tipo de Contrato]],Cat!$G$1:$H$12,2,0)) -> 1 | U11: =IF(TablaTrabajadores[[#This Row],[Tipo de Régimen]]="","",VLOOKUP(TablaTrabajadores[[#This Row],[Tipo de Régimen]],Cat!$J$1:$K$13,2,0)) -> 2 | V11: =ROUND(IF((SUMIF(TablaPercepciones[[#All],[Trabajador]],TablaTrabajadores[[#This Row],[Nombre Trabajador]],TablaPercepciones[[#All],[Importe Gravado]])+SUMIF(TablaPercepciones[[#All],[Trabajador]],TablaTrabajadores[[#This Row],[Nombre Trabajador]],TablaPercepciones[[#All],[o]]))=0,0,SUMIF(TablaPercepciones[[#All],[Trabajador]],TablaTrabajadores[[#This Row],[Nombre Trabajador]],TablaPercepciones[[#All],[Importe Gravado]])+SUMIF(TablaPercepciones[[#All],[Trabajador]],TablaTrabajadores[[#This Row],[Nombre Trabajador]],TablaPercepciones[[#All],[o]])),2) -> #REF! | W11: =ROUND(IF((SUMIF(TablaDeducciones[[#All],[Trabajador]],TablaTrabajadores[[#This Row],[Nombre Trabajador]],TablaDeducciones[[#All],[Importe]]))=0,0,SUMIF(TablaDeducciones[[#All],[Trabajador]],TablaTrabajadores[[#This Row],[Nombre Trabajador]],TablaDeducciones[[#All],[Importe]])),2) -> 0 | X11: =ROUND(IF((SUMIF(TablaOtrosPagos[[#All],[Trabajador]],TablaTrabajadores[[#This Row],[Nombre Trabajador]],TablaOtrosPagos[[#All],[Importe]]))=0,0,SUMIF(TablaOtrosPagos[[#All],[Trabajador]],TablaTrabajadores[[#This Row],[Nombre Trabajador]],TablaOtrosPagos[[#All],[Importe]])),2) -> #REF! | Y11: =IF(OR(TablaOrganismo[Fecha Final de pago]="",TablaTrabajadores[[#This Row],[Fecha Inicio Relación Laboral]]=""),"",CONCATENATE("P",ROUNDDOWN((TablaOrganismo[Fecha Final de pago]-TablaTrabajadores[[#This Row],[Fecha Inicio Relación Laboral]])/7,0),"W")) -> P121W | Z11: =COUNTIF(TablaPercepciones[[#All],[Trabajador]],TablaTrabajadores[[#This Row],[Nombre Trabajador]]) -> 4 | AA11: =COUNTIF(TablaDeducciones[[#All],[Trabajador]],TablaTrabajadores[[#This Row],[Nombre Trabajador]]) -> 0 | AB11: =ROUND(IF((SUMIF(TablaPercepciones[[#All],[Trabajador]],TablaTrabajadores[[#This Row],[Nombre Trabajador]],TablaPercepciones[[#All],[Importe Gravado]]))=0,0,SUMIF(TablaPercepciones[[#All],[Trabajador]],TablaTrabajadores[[#This Row],[Nombre Trabajador]],TablaPercepciones[[#All],[Importe Gravado]])),2) -> #REF! | AC11: =ROUND(IF((SUMIF(TablaPercepciones[[#All],[Trabajador]],TablaTrabajadores[[#This Row],[Nombre Trabajador]],TablaPercepciones[[#All],[o]]))=0,0,SUMIF(TablaPercepciones[[#All],[Trabajador]],TablaTrabajadores[[#This Row],[Nombre Trabajador]],TablaPercepciones[[#All],[o]])),2) -> #REF! | AD11: =ROUND(IF(SUMIFS(TablaDeducciones[[#All],[Importe]],TablaDeducciones[[#All],[Trabajador]],TablaTrabajadores[[#This Row],[Nombre Trabajador]],TablaDeducciones[[#All],[Clave Deducción]],"<>002")=0,0,SUMIFS(TablaDeducciones[[#All],[Importe]],TablaDeducciones[[#All],[Trabajador]],TablaTrabajadores[[#This Row],[Nombre Trabajador]],TablaDeducciones[[#All],[Clave Deducción]],"<>002")),2) -> 0 | AE11: =ROUND(IF((SUMIFS(TablaDeducciones[[#All],[Importe]],TablaDeducciones[[#All],[Trabajador]],TablaTrabajadores[[#This Row],[Nombre Trabajador]],TablaDeducciones[[#All],[Clave Deducción]],"=002"))=0,0,SUMIFS(TablaDeducciones[[#All],[Importe]],TablaDeducciones[[#All],[Trabajador]],TablaTrabajadores[[#This Row],[Nombre Trabajador]],TablaDeducciones[[#All],[Clave Deducción]],"=002")),2) -> 0 | AF11: =IF(TablaTrabajadores[[#This Row],[Origen del Recurso]]="","",VLOOKUP(TablaTrabajadores[[#This Row],[Origen del Recurso]],Cat!Y:Z,2,0)) -> IP | AG11: =IF(TablaTrabajadores[[#This Row],[Entidad Federativa]]="","",VLOOKUP(TablaTrabajadores[[#This Row],[Entidad Federativa]],Cat!AB:AC,2,0)) -> CHP | AH11: =COUNTIF(TablaHorasExtra[[#All],[Trabajador]],TablaTrabajadores[[#This Row],[Nombre Trabajador]]) -> 0 | AI11: =COUNTIF(TablaOtrosPagos[[#All],[Trabajador]],TablaTrabajadores[[#This Row],[Nombre Trabajador]]) -> 1 | AJ11: =IF(TablaTrabajadores[[#This Row],[Tipo de Jornada]]="","",VLOOKUP(TablaTrabajadores[[#This Row],[Tipo de Jornada]],Cat!AK:AL,2,0)) -> 1 | AK11: =ROUND(IFERROR(SUMIFS(TablaPercepciones[[#All],[Importe Gravado]],TablaPercepciones[[#All],[Trabajador]],TablaTrabajadores[[#This Row],[Nombre Trabajador]],TablaPercepciones[[#All],[Clave Percepción]],"<>022",TablaPercepciones[[#All],[Clave Percepción]],"<>023",TablaPercepciones[[#All],[Clave Percepción]],"<>025",TablaPercepciones[[#All],[Clave Percepción]],"<>044"),0)+IFERROR(SUMIFS(TablaPercepciones[[#All],[o]],TablaPercepciones[[#All],[Trabajador]],TablaTrabajadores[[#This Row],[Nombre Trabajador]],TablaPercepciones[[#All],[Clave Percepción]],"<>022",TablaPercepciones[[#All],[Clave Percepción]],"<>023",TablaPercepciones[[#All],[Clave Percepción]],"<>025",TablaPercepciones[[#All],[Clave Percepción]],"<>044"),0),2) -> 0 | AL11: =ROUND(IFERROR(SUMIFS(TablaPercepciones[[#All],[Importe Gravado]],TablaPercepciones[[#All],[Trabajador]],TablaTrabajadores[[#This Row],[Nombre Trabajador]],TablaPercepciones[[#All],[Clave Percepción]],"=022"),0)+IFERROR(SUMIFS(TablaPercepciones[[#All],[Importe Gravado]],TablaPercepciones[[#All],[Trabajador]],TablaTrabajadores[[#This Row],[Nombre Trabajador]],TablaPercepciones[[#All],[Clave Percepción]],"=023"),0)+IFERROR(SUMIFS(TablaPercepciones[[#All],[Importe Gravado]],TablaPercepciones[[#All],[Trabajador]],TablaTrabajadores[[#This Row],[Nombre Trabajador]],TablaPercepciones[[#All],[Clave Percepción]],"=025"),0)+IFERROR(SUMIFS(TablaPercepciones[[#All],[o]],TablaPercepciones[[#All],[Trabajador]],TablaTrabajadores[[#This Row],[Nombre Trabajador]],TablaPercepciones[[#All],[Clave Percepción]],"=022"),0)+IFERROR(SUMIFS(TablaPercepciones[[#All],[o]],TablaPercepciones[[#All],[Trabajador]],TablaTrabajadores[[#This Row],[Nombre Trabajador]],TablaPercepciones[[#All],[Clave Percepción]],"=023"),0)+IFERROR(SUMIFS(TablaPercepciones[[#All],[o]],TablaPercepciones[[#All],[Trabajador]],TablaTrabajadores[[#This Row],[Nombre Trabajador]],TablaPercepciones[[#All],[Clave Percepción]],"=025"),0),2) -> 0 | AM11: =ROUND(IFERROR(SUMIFS(TablaPercepciones[[#All],[Importe Gravado]],TablaPercepciones[[#All],[Trabajador]],TablaTrabajadores[[#This Row],[Nombre Trabajador]],TablaPercepciones[[#All],[Clave Percepción]],"=039"),0)+IFERROR(SUMIFS(TablaPercepciones[[#All],[Importe Gravado]],TablaPercepciones[[#All],[Trabajador]],TablaTrabajadores[[#This Row],[Nombre Trabajador]],TablaPercepciones[[#All],[Clave Percepción]],"=044"),0)+IFERROR(SUMIFS(TablaPercepciones[[#All],[o]],TablaPercepciones[[#All],[Trabajador]],TablaTrabajadores[[#This Row],[Nombre Trabajador]],TablaPercepciones[[#All],[Clave Percepción]],"=039"),0)+IFERROR(SUMIFS(TablaPercepciones[[#All],[o]],TablaPercepciones[[#All],[Trabajador]],TablaTrabajadores[[#This Row],[Nombre Trabajador]],TablaPercepciones[[#All],[Clave Percepción]],"=044"),0),2) -> 0 | AN11: Diurna
A12: 11 | B12: RACA710517C72 | C12: RAMIREZ CRUZ ANISETO | D12: RACA710517HCSMRN00 | E12: 71027100818 | F12: 37104 | G12: Contrato de trabajo por tiempo indeterminado | H12: Sueldos | I12: 61 | J12: OFICINA DE PRODUCCION | K12: CONDUCTOR A | L12: 1 | M12: 167.06316 | N12: Ingresos propios | P12: Chiapas | Q12: anisetoramirez@msn.com | R12: canal10humanos@gmail.com | T12: =IF(TablaTrabajadores[[#This Row],[Tipo de Contrato]]="","",VLOOKUP(TablaTrabajadores[[#This Row],[Tipo de Contrato]],Cat!$G$1:$H$12,2,0)) -> 1 | U12: =IF(TablaTrabajadores[[#This Row],[Tipo de Régimen]]="","",VLOOKUP(TablaTrabajadores[[#This Row],[Tipo de Régimen]],Cat!$J$1:$K$13,2,0)) -> 2 | V12: =ROUND(IF((SUMIF(TablaPercepciones[[#All],[Trabajador]],TablaTrabajadores[[#This Row],[Nombre Trabajador]],TablaPercepciones[[#All],[Importe Gravado]])+SUMIF(TablaPercepciones[[#All],[Trabajador]],TablaTrabajadores[[#This Row],[Nombre Trabajador]],TablaPercepciones[[#All],[o]]))=0,0,SUMIF(TablaPercepciones[[#All],[Trabajador]],TablaTrabajadores[[#This Row],[Nombre Trabajador]],TablaPercepciones[[#All],[Importe Gravado]])+SUMIF(TablaPercepciones[[#All],[Trabajador]],TablaTrabajadores[[#This Row],[Nombre Trabajador]],TablaPercepciones[[#All],[o]])),2) -> #REF! | W12: =ROUND(IF((SUMIF(TablaDeducciones[[#All],[Trabajador]],TablaTrabajadores[[#This Row],[Nombre Trabajador]],TablaDeducciones[[#All],[Importe]]))=0,0,SUMIF(TablaDeducciones[[#All],[Trabajador]],TablaTrabajadores[[#This Row],[Nombre Trabajador]],TablaDeducciones[[#All],[Importe]])),2) -> #REF! | X12: =ROUND(IF((SUMIF(TablaOtrosPagos[[#All],[Trabajador]],TablaTrabajadores[[#This Row],[Nombre Trabajador]],TablaOtrosPagos[[#All],[Importe]]))=0,0,SUMIF(TablaOtrosPagos[[#All],[Trabajador]],TablaTrabajadores[[#This Row],[Nombre Trabajador]],TablaOtrosPagos[[#All],[Importe]])),2) -> #REF! | Y12: =IF(OR(TablaOrganismo[Fecha Final de pago]="",TablaTrabajadores[[#This Row],[Fecha Inicio Relación Laboral]]=""),"",CONCATENATE("P",ROUNDDOWN((TablaOrganismo[Fecha Final de pago]-TablaTrabajadores[[#This Row],[Fecha Inicio Relación Laboral]])/7,0),"W")) -> P1034W | Z12: =COUNTIF(TablaPercepciones[[#All],[Trabajador]],TablaTrabajadores[[#This Row],[Nombre Trabajador]]) -> 4 | AA12: =COUNTIF(TablaDeducciones[[#All],[Trabajador]],TablaTrabajadores[[#This Row],[Nombre Trabajador]]) -> 1 | AB12: =ROUND(IF((SUMIF(TablaPercepciones[[#All],[Trabajador]],TablaTrabajadores[[#This Row],[Nombre Trabajador]],TablaPercepciones[[#All],[Importe Gravado]]))=0,0,SUMIF(TablaPercepciones[[#All],[Trabajador]],TablaTrabajadores[[#This Row],[Nombre Trabajador]],TablaPercepciones[[#All],[Importe Gravado]])),2) -> #REF! | AC12: =ROUND(IF((SUMIF(TablaPercepciones[[#All],[Trabajador]],TablaTrabajadores[[#This Row],[Nombre Trabajador]],TablaPercepciones[[#All],[o]]))=0,0,SUMIF(TablaPercepciones[[#All],[Trabajador]],TablaTrabajadores[[#This Row],[Nombre Trabajador]],TablaPercepciones[[#All],[o]])),2) -> #REF! | AD12: =ROUND(IF(SUMIFS(TablaDeducciones[[#All],[Importe]],TablaDeducciones[[#All],[Trabajador]],TablaTrabajadores[[#This Row],[Nombre Trabajador]],TablaDeducciones[[#All],[Clave Deducción]],"<>002")=0,0,SUMIFS(TablaDeducciones[[#All],[Importe]],TablaDeducciones[[#All],[Trabajador]],TablaTrabajadores[[#This Row],[Nombre Trabajador]],TablaDeducciones[[#All],[Clave Deducción]],"<>002")),2) -> #REF! | AE12: =ROUND(IF((SUMIFS(TablaDeducciones[[#All],[Importe]],TablaDeducciones[[#All],[Trabajador]],TablaTrabajadores[[#This Row],[Nombre Trabajador]],TablaDeducciones[[#All],[Clave Deducción]],"=002"))=0,0,SUMIFS(TablaDeducciones[[#All],[Importe]],TablaDeducciones[[#All],[Trabajador]],TablaTrabajadores[[#This Row],[Nombre Trabajador]],TablaDeducciones[[#All],[Clave Deducción]],"=002")),2) -> 0 | AF12: =IF(TablaTrabajadores[[#This Row],[Origen del Recurso]]="","",VLOOKUP(TablaTrabajadores[[#This Row],[Origen del Recurso]],Cat!Y:Z,2,0)) -> IP | AG12: =IF(TablaTrabajadores[[#This Row],[Entidad Federativa]]="","",VLOOKUP(TablaTrabajadores[[#This Row],[Entidad Federativa]],Cat!AB:AC,2,0)) -> CHP | AH12: =COUNTIF(TablaHorasExtra[[#All],[Trabajador]],TablaTrabajadores[[#This Row],[Nombre Trabajador]]) -> 0 | AI12: =COUNTIF(TablaOtrosPagos[[#All],[Trabajador]],TablaTrabajadores[[#This Row],[Nombre Trabajador]]) -> 1 | AJ12: =IF(TablaTrabajadores[[#This Row],[Tipo de Jornada]]="","",VLOOKUP(TablaTrabajadores[[#This Row],[Tipo de Jornada]],Cat!AK:AL,2,0)) -> 1 | AK12: =ROUND(IFERROR(SUMIFS(TablaPercepciones[[#All],[Importe Gravado]],TablaPercepciones[[#All],[Trabajador]],TablaTrabajadores[[#This Row],[Nombre Trabajador]],TablaPercepciones[[#All],[Clave Percepción]],"<>022",TablaPercepciones[[#All],[Clave Percepción]],"<>023",TablaPercepciones[[#All],[Clave Percepción]],"<>025",TablaPercepciones[[#All],[Clave Percepción]],"<>044"),0)+IFERROR(SUMIFS(TablaPercepciones[[#All],[o]],TablaPercepciones[[#All],[Trabajador]],TablaTrabajadores[[#This Row],[Nombre Trabajador]],TablaPercepciones[[#All],[Clave Percepción]],"<>022",TablaPercepciones[[#All],[Clave Percepción]],"<>023",TablaPercepciones[[#All],[Clave Percepción]],"<>025",TablaPercepciones[[#All],[Clave Percepción]],"<>044"),0),2) -> 0 | AL12: =ROUND(IFERROR(SUMIFS(TablaPercepciones[[#All],[Importe Gravado]],TablaPercepciones[[#All],[Trabajador]],TablaTrabajadores[[#This Row],[Nombre Trabajador]],TablaPercepciones[[#All],[Clave Percepción]],"=022"),0)+IFERROR(SUMIFS(TablaPercepciones[[#All],[Importe Gravado]],TablaPercepciones[[#All],[Trabajador]],TablaTrabajadores[[#This Row],[Nombre Trabajador]],TablaPercepciones[[#All],[Clave Percepción]],"=023"),0)+IFERROR(SUMIFS(TablaPercepciones[[#All],[Importe Gravado]],TablaPercepciones[[#All],[Trabajador]],TablaTrabajadores[[#This Row],[Nombre Trabajador]],TablaPercepciones[[#All],[Clave Percepción]],"=025"),0)+IFERROR(SUMIFS(TablaPercepciones[[#All],[o]],TablaPercepciones[[#All],[Trabajador]],TablaTrabajadores[[#This Row],[Nombre Trabajador]],TablaPercepciones[[#All],[Clave Percepción]],"=022"),0)+IFERROR(SUMIFS(TablaPercepciones[[#All],[o]],TablaPercepciones[[#All],[Trabajador]],TablaTrabajadores[[#This Row],[Nombre Trabajador]],TablaPercepciones[[#All],[Clave Percepción]],"=023"),0)+IFERROR(SUMIFS(TablaPercepciones[[#All],[o]],TablaPercepciones[[#All],[Trabajador]],TablaTrabajadores[[#This Row],[Nombre Trabajador]],TablaPercepciones[[#All],[Clave Percepción]],"=025"),0),2) -> 0 | AM12: =ROUND(IFERROR(SUMIFS(TablaPercepciones[[#All],[Importe Gravado]],TablaPercepciones[[#All],[Trabajador]],TablaTrabajadores[[#This Row],[Nombre Trabajador]],TablaPercepciones[[#All],[Clave Percepción]],"=039"),0)+IFERROR(SUMIFS(TablaPercepciones[[#All],[Importe Gravado]],TablaPercepciones[[#All],[Trabajador]],TablaTrabajadores[[#This Row],[Nombre Trabajador]],TablaPercepciones[[#All],[Clave Percepción]],"=044"),0)+IFERROR(SUMIFS(TablaPercepciones[[#All],[o]],TablaPercepciones[[#All],[Trabajador]],TablaTrabajadores[[#This Row],[Nombre Trabajador]],TablaPercepciones[[#All],[Clave Percepción]],"=039"),0)+IFERROR(SUMIFS(TablaPercepciones[[#All],[o]],TablaPercepciones[[#All],[Trabajador]],TablaTrabajadores[[#This Row],[Nombre Trabajador]],TablaPercepciones[[#All],[Clave Percepción]],"=044"),0),2) -> 0 | AN12: Diurna
A13: 12 | B13: RACI920218QA2 | C13: RAMOS CALVO IVAN ALEJANDRO | D13: RACI920218HCSMLV04 | E13: 1199266030 | F13: 44256 | G13: Contrato de trabajo por tiempo indeterminado | H13: Sueldos | I13: 5203 | J13: RECURSOS FINANCIEROS Y PLANEACIÓN | K13: RECEPCIONISTA | L13: 1 | M13: 230.94 | N13: Ingresos propios | P13: Chiapas | Q13: arcalvo@gmail.com | R13: canal10humanos@gmail.com | T13: =IF(TablaTrabajadores[[#This Row],[Tipo de Contrato]]="","",VLOOKUP(TablaTrabajadores[[#This Row],[Tipo de Contrato]],Cat!$G$1:$H$12,2,0)) -> 1 | U13: =IF(TablaTrabajadores[[#This Row],[Tipo de Régimen]]="","",VLOOKUP(TablaTrabajadores[[#This Row],[Tipo de Régimen]],Cat!$J$1:$K$13,2,0)) -> 2 | V13: =ROUND(IF((SUMIF(TablaPercepciones[[#All],[Trabajador]],TablaTrabajadores[[#This Row],[Nombre Trabajador]],TablaPercepciones[[#All],[Importe Gravado]])+SUMIF(TablaPercepciones[[#All],[Trabajador]],TablaTrabajadores[[#This Row],[Nombre Trabajador]],TablaPercepciones[[#All],[o]]))=0,0,SUMIF(TablaPercepciones[[#All],[Trabajador]],TablaTrabajadores[[#This Row],[Nombre Trabajador]],TablaPercepciones[[#All],[Importe Gravado]])+SUMIF(TablaPercepciones[[#All],[Trabajador]],TablaTrabajadores[[#This Row],[Nombre Trabajador]],TablaPercepciones[[#All],[o]])),2) -> #REF! | W13: =ROUND(IF((SUMIF(TablaDeducciones[[#All],[Trabajador]],TablaTrabajadores[[#This Row],[Nombre Trabajador]],TablaDeducciones[[#All],[Importe]]))=0,0,SUMIF(TablaDeducciones[[#All],[Trabajador]],TablaTrabajadores[[#This Row],[Nombre Trabajador]],TablaDeducciones[[#All],[Importe]])),2) -> 0 | X13: =ROUND(IF((SUMIF(TablaOtrosPagos[[#All],[Trabajador]],TablaTrabajadores[[#This Row],[Nombre Trabajador]],TablaOtrosPagos[[#All],[Importe]]))=0,0,SUMIF(TablaOtrosPagos[[#All],[Trabajador]],TablaTrabajadores[[#This Row],[Nombre Trabajador]],TablaOtrosPagos[[#All],[Importe]])),2) -> #REF! | Y13: =IF(OR(TablaOrganismo[Fecha Final de pago]="",TablaTrabajadores[[#This Row],[Fecha Inicio Relación Laboral]]=""),"",CONCATENATE("P",ROUNDDOWN((TablaOrganismo[Fecha Final de pago]-TablaTrabajadores[[#This Row],[Fecha Inicio Relación Laboral]])/7,0),"W")) -> P13W | Z13: =COUNTIF(TablaPercepciones[[#All],[Trabajador]],TablaTrabajadores[[#This Row],[Nombre Trabajador]]) -> 3 | AA13: =COUNTIF(TablaDeducciones[[#All],[Trabajador]],TablaTrabajadores[[#This Row],[Nombre Trabajador]]) -> 0 | AB13: =ROUND(IF((SUMIF(TablaPercepciones[[#All],[Trabajador]],TablaTrabajadores[[#This Row],[Nombre Trabajador]],TablaPercepciones[[#All],[Importe Gravado]]))=0,0,SUMIF(TablaPercepciones[[#All],[Trabajador]],TablaTrabajadores[[#This Row],[Nombre Trabajador]],TablaPercepciones[[#All],[Importe Gravado]])),2) -> #REF! | AC13: =ROUND(IF((SUMIF(TablaPercepciones[[#All],[Trabajador]],TablaTrabajadores[[#This Row],[Nombre Trabajador]],TablaPercepciones[[#All],[o]]))=0,0,SUMIF(TablaPercepciones[[#All],[Trabajador]],TablaTrabajadores[[#This Row],[Nombre Trabajador]],TablaPercepciones[[#All],[o]])),2) -> #REF! | AD13: =ROUND(IF(SUMIFS(TablaDeducciones[[#All],[Importe]],TablaDeducciones[[#All],[Trabajador]],TablaTrabajadores[[#This Row],[Nombre Trabajador]],TablaDeducciones[[#All],[Clave Deducción]],"<>002")=0,0,SUMIFS(TablaDeducciones[[#All],[Importe]],TablaDeducciones[[#All],[Trabajador]],TablaTrabajadores[[#This Row],[Nombre Trabajador]],TablaDeducciones[[#All],[Clave Deducción]],"<>002")),2) -> 0 | AE13: =ROUND(IF((SUMIFS(TablaDeducciones[[#All],[Importe]],TablaDeducciones[[#All],[Trabajador]],TablaTrabajadores[[#This Row],[Nombre Trabajador]],TablaDeducciones[[#All],[Clave Deducción]],"=002"))=0,0,SUMIFS(TablaDeducciones[[#All],[Importe]],TablaDeducciones[[#All],[Trabajador]],TablaTrabajadores[[#This Row],[Nombre Trabajador]],TablaDeducciones[[#All],[Clave Deducción]],"=002")),2) -> 0 | AF13: =IF(TablaTrabajadores[[#This Row],[Origen del Recurso]]="","",VLOOKUP(TablaTrabajadores[[#This Row],[Origen del Recurso]],Cat!Y:Z,2,0)) -> IP | AG13: =IF(TablaTrabajadores[[#This Row],[Entidad Federativa]]="","",VLOOKUP(TablaTrabajadores[[#This Row],[Entidad Federativa]],Cat!AB:AC,2,0)) -> CHP | AH13: =COUNTIF(TablaHorasExtra[[#All],[Trabajador]],TablaTrabajadores[[#This Row],[Nombre Trabajador]]) -> 0 | AI13: =COUNTIF(TablaOtrosPagos[[#All],[Trabajador]],TablaTrabajadores[[#This Row],[Nombre Trabajador]]) -> 1 | AJ13: =IF(TablaTrabajadores[[#This Row],[Tipo de Jornada]]="","",VLOOKUP(TablaTrabajadores[[#This Row],[Tipo de Jornada]],Cat!AK:AL,2,0)) -> 3 | AK13: =ROUND(IFERROR(SUMIFS(TablaPercepciones[[#All],[Importe Gravado]],TablaPercepciones[[#All],[Trabajador]],TablaTrabajadores[[#This Row],[Nombre Trabajador]],TablaPercepciones[[#All],[Clave Percepción]],"<>022",TablaPercepciones[[#All],[Clave Percepción]],"<>023",TablaPercepciones[[#All],[Clave Percepción]],"<>025",TablaPercepciones[[#All],[Clave Percepción]],"<>044"),0)+IFERROR(SUMIFS(TablaPercepciones[[#All],[o]],TablaPercepciones[[#All],[Trabajador]],TablaTrabajadores[[#This Row],[Nombre Trabajador]],TablaPercepciones[[#All],[Clave Percepción]],"<>022",TablaPercepciones[[#All],[Clave Percepción]],"<>023",TablaPercepciones[[#All],[Clave Percepción]],"<>025",TablaPercepciones[[#All],[Clave Percepción]],"<>044"),0),2) -> 0 | AL13: =ROUND(IFERROR(SUMIFS(TablaPercepciones[[#All],[Importe Gravado]],TablaPercepciones[[#All],[Trabajador]],TablaTrabajadores[[#This Row],[Nombre Trabajador]],TablaPercepciones[[#All],[Clave Percepción]],"=022"),0)+IFERROR(SUMIFS(TablaPercepciones[[#All],[Importe Gravado]],TablaPercepciones[[#All],[Trabajador]],TablaTrabajadores[[#This Row],[Nombre Trabajador]],TablaPercepciones[[#All],[Clave Percepción]],"=023"),0)+IFERROR(SUMIFS(TablaPercepciones[[#All],[Importe Gravado]],TablaPercepciones[[#All],[Trabajador]],TablaTrabajadores[[#This Row],[Nombre Trabajador]],TablaPercepciones[[#All],[Clave Percepción]],"=025"),0)+IFERROR(SUMIFS(TablaPercepciones[[#All],[o]],TablaPercepciones[[#All],[Trabajador]],TablaTrabajadores[[#This Row],[Nombre Trabajador]],TablaPercepciones[[#All],[Clave Percepción]],"=022"),0)+IFERROR(SUMIFS(TablaPercepciones[[#All],[o]],TablaPercepciones[[#All],[Trabajador]],TablaTrabajadores[[#This Row],[Nombre Trabajador]],TablaPercepciones[[#All],[Clave Percepción]],"=023"),0)+IFERROR(SUMIFS(TablaPercepciones[[#All],[o]],TablaPercepciones[[#All],[Trabajador]],TablaTrabajadores[[#This Row],[Nombre Trabajador]],TablaPercepciones[[#All],[Clave Percepción]],"=025"),0),2) -> 0 | AM13: =ROUND(IFERROR(SUMIFS(TablaPercepciones[[#All],[Importe Gravado]],TablaPercepciones[[#All],[Trabajador]],TablaTrabajadores[[#This Row],[Nombre Trabajador]],TablaPercepciones[[#All],[Clave Percepción]],"=039"),0)+IFERROR(SUMIFS(TablaPercepciones[[#All],[Importe Gravado]],TablaPercepciones[[#All],[Trabajador]],TablaTrabajadores[[#This Row],[Nombre Trabajador]],TablaPercepciones[[#All],[Clave Percepción]],"=044"),0)+IFERROR(SUMIFS(TablaPercepciones[[#All],[o]],TablaPercepciones[[#All],[Trabajador]],TablaTrabajadores[[#This Row],[Nombre Trabajador]],TablaPercepciones[[#All],[Clave Percepción]],"=039"),0)+IFERROR(SUMIFS(TablaPercepciones[[#All],[o]],TablaPercepciones[[#All],[Trabajador]],TablaTrabajadores[[#This Row],[Nombre Trabajador]],TablaPercepciones[[#All],[Clave Percepción]],"=044"),0),2) -> 0 | AN13: Mixta
... A19: 18 | B19: YALL820202E35 | C19: YAÑEZ LOPEZ LORENA | D19: YALL820202MCSXPR09 | E19: 12038221292 | F19: 42491 | G19: Contrato de trabajo por tiempo indeterminado | H19: Sueldos | I19: 5174 | J19: AREA DE RECURSOS HUMANOS | K19: RECEPCIONISTA | L19: 1 | M19: 225.40195 | N19: Ingresos propios | P19: Chiapas | Q19: lorena_02ma@hotmail.com | R19: canal10humanos@gmail.com | T19: =IF(TablaTrabajadores[[#This Row],[Tipo de Contrato]]="","",VLOOKUP(TablaTrabajadores[[#This Row],[Tipo de Contrato]],Cat!$G$1:$H$12,2,0)) -> 1 | U19: =IF(TablaTrabajadores[[#This Row],[Tipo de Régimen]]="","",VLOOKUP(TablaTrabajadores[[#This Row],[Tipo de Régimen]],Cat!$J$1:$K$13,2,0)) -> 2 | V19: =ROUND(IF((SUMIF(TablaPercepciones[[#All],[Trabajador]],TablaTrabajadores[[#This Row],[Nombre Trabajador]],TablaPercepciones[[#All],[Importe Gravado]])+SUMIF(TablaPercepciones[[#All],[Trabajador]],TablaTrabajadores[[#This Row],[Nombre Trabajador]],TablaPercepciones[[#All],[o]]))=0,0,SUMIF(TablaPercepciones[[#All],[Trabajador]],TablaTrabajadores[[#This Row],[Nombre Trabajador]],TablaPercepciones[[#All],[Importe Gravado]])+SUMIF(TablaPercepciones[[#All],[Trabajador]],TablaTrabajadores[[#This Row],[Nombre Trabajador]],TablaPercepciones[[#All],[o]])),2) -> #REF! | W19: =ROUND(IF((SUMIF(TablaDeducciones[[#All],[Trabajador]],TablaTrabajadores[[#This Row],[Nombre Trabajador]],TablaDeducciones[[#All],[Importe]]))=0,0,SUMIF(TablaDeducciones[[#All],[Trabajador]],TablaTrabajadores[[#This Row],[Nombre Trabajador]],TablaDeducciones[[#All],[Importe]])),2) -> #REF! | X19: =ROUND(IF((SUMIF(TablaOtrosPagos[[#All],[Trabajador]],TablaTrabajadores[[#This Row],[Nombre Trabajador]],TablaOtrosPagos[[#All],[Importe]]))=0,0,SUMIF(TablaOtrosPagos[[#All],[Trabajador]],TablaTrabajadores[[#This Row],[Nombre Trabajador]],TablaOtrosPagos[[#All],[Importe]])),2) -> #REF! | Y19: =IF(OR(TablaOrganismo[Fecha Final de pago]="",TablaTrabajadores[[#This Row],[Fecha Inicio Relación Laboral]]=""),"",CONCATENATE("P",ROUNDDOWN((TablaOrganismo[Fecha Final de pago]-TablaTrabajadores[[#This Row],[Fecha Inicio Relación Laboral]])/7,0),"W")) -> P265W | Z19: =COUNTIF(TablaPercepciones[[#All],[Trabajador]],TablaTrabajadores[[#This Row],[Nombre Trabajador]]) -> 4 | AA19: =COUNTIF(TablaDeducciones[[#All],[Trabajador]],TablaTrabajadores[[#This Row],[Nombre Trabajador]]) -> 1 | AB19: =ROUND(IF((SUMIF(TablaPercepciones[[#All],[Trabajador]],TablaTrabajadores[[#This Row],[Nombre Trabajador]],TablaPercepciones[[#All],[Importe Gravado]]))=0,0,SUMIF(TablaPercepciones[[#All],[Trabajador]],TablaTrabajadores[[#This Row],[Nombre Trabajador]],TablaPercepciones[[#All],[Importe Gravado]])),2) -> #REF! | AC19: =ROUND(IF((SUMIF(TablaPercepciones[[#All],[Trabajador]],TablaTrabajadores[[#This Row],[Nombre Trabajador]],TablaPercepciones[[#All],[o]]))=0,0,SUMIF(TablaPercepciones[[#All],[Trabajador]],TablaTrabajadores[[#This Row],[Nombre Trabajador]],TablaPercepciones[[#All],[o]])),2) -> #REF! | AD19: =ROUND(IF(SUMIFS(TablaDeducciones[[#All],[Importe]],TablaDeducciones[[#All],[Trabajador]],TablaTrabajadores[[#This Row],[Nombre Trabajador]],TablaDeducciones[[#All],[Clave Deducción]],"<>002")=0,0,SUMIFS(TablaDeducciones[[#All],[Importe]],TablaDeducciones[[#All],[Trabajador]],TablaTrabajadores[[#This Row],[Nombre Trabajador]],TablaDeducciones[[#All],[Clave Deducción]],"<>002")),2) -> #REF! | AE19: =ROUND(IF((SUMIFS(TablaDeducciones[[#All],[Importe]],TablaDeducciones[[#All],[Trabajador]],TablaTrabajadores[[#This Row],[Nombre Trabajador]],TablaDeducciones[[#All],[Clave Deducción]],"=002"))=0,0,SUMIFS(TablaDeducciones[[#All],[Importe]],TablaDeducciones[[#All],[Trabajador]],TablaTrabajadores[[#This Row],[Nombre Trabajador]],TablaDeducciones[[#All],[Clave Deducción]],"=002")),2) -> 0 | AF19: =IF(TablaTrabajadores[[#This Row],[Origen del Recurso]]="","",VLOOKUP(TablaTrabajadores[[#This Row],[Origen del Recurso]],Cat!Y:Z,2,0)) -> IP | AG19: =IF(TablaTrabajadores[[#This Row],[Entidad Federativa]]="","",VLOOKUP(TablaTrabajadores[[#This Row],[Entidad Federativa]],Cat!AB:AC,2,0)) -> CHP | AH19: =COUNTIF(TablaHorasExtra[[#All],[Trabajador]],TablaTrabajadores[[#This Row],[Nombre Trabajador]]) -> 0 | AI19: =COUNTIF(TablaOtrosPagos[[#All],[Trabajador]],TablaTrabajadores[[#This Row],[Nombre Trabajador]]) -> 1 | AJ19: =IF(TablaTrabajadores[[#This Row],[Tipo de Jornada]]="","",VLOOKUP(TablaTrabajadores[[#This Row],[Tipo de Jornada]],Cat!AK:AL,2,0)) -> 1 | AK19: =ROUND(IFERROR(SUMIFS(TablaPercepciones[[#All],[Importe Gravado]],TablaPercepciones[[#All],[Trabajador]],TablaTrabajadores[[#This Row],[Nombre Trabajador]],TablaPercepciones[[#All],[Clave Percepción]],"<>022",TablaPercepciones[[#All],[Clave Percepción]],"<>023",TablaPercepciones[[#All],[Clave Percepción]],"<>025",TablaPercepciones[[#All],[Clave Percepción]],"<>044"),0)+IFERROR(SUMIFS(TablaPercepciones[[#All],[o]],TablaPercepciones[[#All],[Trabajador]],TablaTrabajadores[[#This Row],[Nombre Trabajador]],TablaPercepciones[[#All],[Clave Percepción]],"<>022",TablaPercepciones[[#All],[Clave Percepción]],"<>023",TablaPercepciones[[#All],[Clave Percepción]],"<>025",TablaPercepciones[[#All],[Clave Percepción]],"<>044"),0),2) -> 0 | AL19: =ROUND(IFERROR(SUMIFS(TablaPercepciones[[#All],[Importe Gravado]],TablaPercepciones[[#All],[Trabajador]],TablaTrabajadores[[#This Row],[Nombre Trabajador]],TablaPercepciones[[#All],[Clave Percepción]],"=022"),0)+IFERROR(SUMIFS(TablaPercepciones[[#All],[Importe Gravado]],TablaPercepciones[[#All],[Trabajador]],TablaTrabajadores[[#This Row],[Nombre Trabajador]],TablaPercepciones[[#All],[Clave Percepción]],"=023"),0)+IFERROR(SUMIFS(TablaPercepciones[[#All],[Importe Gravado]],TablaPercepciones[[#All],[Trabajador]],TablaTrabajadores[[#This Row],[Nombre Trabajador]],TablaPercepciones[[#All],[Clave Percepción]],"=025"),0)+IFERROR(SUMIFS(TablaPercepciones[[#All],[o]],TablaPercepciones[[#All],[Trabajador]],TablaTrabajadores[[#This Row],[Nombre Trabajador]],TablaPercepciones[[#All],[Clave Percepción]],"=022"),0)+IFERROR(SUMIFS(TablaPercepciones[[#All],[o]],TablaPercepciones[[#All],[Trabajador]],TablaTrabajadores[[#This Row],[Nombre Trabajador]],TablaPercepciones[[#All],[Clave Percepción]],"=023"),0)+IFERROR(SUMIFS(TablaPercepciones[[#All],[o]],TablaPercepciones[[#All],[Trabajador]],TablaTrabajadores[[#This Row],[Nombre Trabajador]],TablaPercepciones[[#All],[Clave Percepción]],"=025"),0),2) -> 0 | AM19: =ROUND(IFERROR(SUMIFS(TablaPercepciones[[#All],[Importe Gravado]],TablaPercepciones[[#All],[Trabajador]],TablaTrabajadores[[#This Row],[Nombre Trabajador]],TablaPercepciones[[#All],[Clave Percepción]],"=039"),0)+IFERROR(SUMIFS(TablaPercepciones[[#All],[Importe Gravado]],TablaPercepciones[[#All],[Trabajador]],TablaTrabajadores[[#This Row],[Nombre Trabajador]],TablaPercepciones[[#All],[Clave Percepción]],"=044"),0)+IFERROR(SUMIFS(TablaPercepciones[[#All],[o]],TablaPercepciones[[#All],[Trabajador]],TablaTrabajadores[[#This Row],[Nombre Trabajador]],TablaPercepciones[[#All],[Clave Percepción]],"=039"),0)+IFERROR(SUMIFS(TablaPercepciones[[#All],[o]],TablaPercepciones[[#All],[Trabajador]],TablaTrabajadores[[#This Row],[Nombre Trabajador]],TablaPercepciones[[#All],[Clave Percepción]],"=044"),0),2) -> 0 | AN19: Diurna

Sheet Percepciones
A1: Trabajador | B1: Percepción | C1: Clave | D1: Concepto | E1: Importe Gravado | F1: o | G1: Clave Percepción
A2: CAMACHO OVANDO ALAN ULISES | B2: Sueldos, Salarios Rayas y Jornales | C2: 1 | D2: Sueldos y Salarios | E2: =SUMIFS(#REF!,#REF!,TablaPercepciones[[#This Row],[Trabajador]]) -> #REF! | F2: 0 | G2: =IF(TablaPercepciones[[#This Row],[Percepción]]="","",VLOOKUP(TablaPercepciones[[#This Row],[Percepción]],Cat!$M$2:$N$42,2,0)) -> 1
A3: ENRIQUEZ CONSTANTINO SILVIA | B3: Sueldos, Salarios Rayas y Jornales | C3: 1 | D3: Sueldos y Salarios | E3: =SUMIFS(#REF!,#REF!,TablaPercepciones[[#This Row],[Trabajador]]) -> #REF! | F3: 0 | G3: =IF(TablaPercepciones[[#This Row],[Percepción]]="","",VLOOKUP(TablaPercepciones[[#This Row],[Percepción]],Cat!$M$2:$N$42,2,0)) -> 1
A4: GOMEZ HERNANDEZ SANTIAGO CRISTOBAL | B4: Sueldos, Salarios Rayas y Jornales | C4: 1 | D4: Sueldos y Salarios | E4: =SUMIFS(#REF!,#REF!,TablaPercepciones[[#This Row],[Trabajador]]) -> #REF! | F4: 0 | G4: =IF(TablaPercepciones[[#This Row],[Percepción]]="","",VLOOKUP(TablaPercepciones[[#This Row],[Percepción]],Cat!$M$2:$N$42,2,0)) -> 1
A5: GOMEZ LOPEZ JUAN | B5: Sueldos, Salarios Rayas y Jornales | C5: 1 | D5: Sueldos y Salarios | E5: =SUMIFS(#REF!,#REF!,TablaPercepciones[[#This Row],[Trabajador]]) -> #REF! | F5: 0 | G5: =IF(TablaPercepciones[[#This Row],[Percepción]]="","",VLOOKUP(TablaPercepciones[[#This Row],[Percepción]],Cat!$M$2:$N$42,2,0)) -> 1
A6: GONZALEZ ARCE EDUARDO | B6: Sueldos, Salarios Rayas y Jornales | C6: 1 | D6: Sueldos y Salarios | E6: =SUMIFS(#REF!,#REF!,TablaPercepciones[[#This Row],[Trabajador]]) -> #REF! | F6: 0 | G6: =IF(TablaPercepciones[[#This Row],[Percepción]]="","",VLOOKUP(TablaPercepciones[[#This Row],[Percepción]],Cat!$M$2:$N$42,2,0)) -> 1
A7: LEEP ARRIAGA SEMEIN AGUSTIN | B7: Sueldos, Salarios Rayas y Jornales | C7: 1 | D7: Sueldos y Salarios | E7: =SUMIFS(#REF!,#REF!,TablaPercepciones[[#This Row],[Trabajador]]) -> #REF! | F7: 0 | G7: =IF(TablaPercepciones[[#This Row],[Percepción]]="","",VLOOKUP(TablaPercepciones[[#This Row],[Percepción]],Cat!$M$2:$N$42,2,0)) -> 1
A8: LOPEZ MENDEZ LETICIA GUADALUPE | B8: Sueldos, Salarios Rayas y Jornales | C8: 1 | D8: Sueldos y Salarios | E8: =SUMIFS(#REF!,#REF!,TablaPercepciones[[#This Row],[Trabajador]]) -> #REF! | F8: 0 | G8: =IF(TablaPercepciones[[#This Row],[Percepción]]="","",VLOOKUP(TablaPercepciones[[#This Row],[Percepción]],Cat!$M$2:$N$42,2,0)) -> 1
A9: LOPEZ OVANDO LEANDRA GUADALUPE | B9: Sueldos, Salarios Rayas y Jornales | C9: 1 | D9: Sueldos y Salarios | E9: =SUMIFS(#REF!,#REF!,TablaPercepciones[[#This Row],[Trabajador]]) -> #REF! | F9: 0 | G9: =IF(TablaPercepciones[[#This Row],[Percepción]]="","",VLOOKUP(TablaPercepciones[[#This Row],[Percepción]],Cat!$M$2:$N$42,2,0)) -> 1
A10: MENDEZ SANCHEZ MIGUEL | B10: Sueldos, Salarios Rayas y Jornales | C10: 1 | D10: Sueldos y Salarios | E10: =SUMIFS(#REF!,#REF!,TablaPercepciones[[#This Row],[Trabajador]]) -> #REF! | F10: 0 | G10: =IF(TablaPercepciones[[#This Row],[Percepción]]="","",VLOOKUP(TablaPercepciones[[#This Row],[Percepción]],Cat!$M$2:$N$42,2,0)) -> 1
A11: NAJERA NAJERA GREGORIO CESAR | B11: Sueldos, Salarios Rayas y Jornales | C11: 1 | D11: Sueldos y Salarios | E11: =SUMIFS(#REF!,#REF!,TablaPercepciones[[#This Row],[Trabajador]]) -> #REF! | F11: 0 | G11: =IF(TablaPercepciones[[#This Row],[Percepción]]="","",VLOOKUP(TablaPercepciones[[#This Row],[Percepción]],Cat!$M$2:$N$42,2,0)) -> 1
A12: RAMIREZ CRUZ ANISETO | B12: Sueldos, Salarios Rayas y Jornales | C12: 1 | D12: Sueldos y Salarios | E12: =SUMIFS(#REF!,#REF!,TablaPercepciones[[#This Row],[Trabajador]]) -> #REF! | F12: 0 | G12: =IF(TablaPercepciones[[#This Row],[Percepción]]="","",VLOOKUP(TablaPercepciones[[#This Row],[Percepción]],Cat!$M$2:$N$42,2,0)) -> 1
A13: RAMOS CALVO IVAN ALEJANDRO | B13: Sueldos, Salarios Rayas y Jornales | C13: 1 | D13: Sueldos y Salarios | E13: =SUMIFS(#REF!,#REF!,TablaPercepciones[[#This Row],[Trabajador]]) -> #REF! | F13: 0 | G13: =IF(TablaPercepciones[[#This Row],[Percepción]]="","",VLOOKUP(TablaPercepciones[[#This Row],[Percepción]],Cat!$M$2:$N$42,2,0)) -> 1
... A19: YAÑEZ LOPEZ LORENA | B19: Sueldos, Salarios Rayas y Jornales | C19: 1 | D19: Sueldos y Salarios | E19: =SUMIFS(#REF!,#REF!,TablaPercepciones[[#This Row],[Trabajador]]) -> #REF! | F19: 0 | G19: =IF(TablaPercepciones[[#This Row],[Percepción]]="","",VLOOKUP(TablaPercepciones[[#This Row],[Percepción]],Cat!$M$2:$N$42,2,0)) -> 1
A20: CAMACHO OVANDO ALAN ULISES | B20: Otros ingresos por salarios | C20: 29 | D20: Previsión Social | E20: 0 | F20: =SUMIFS(#REF!,#REF!,TablaPercepciones[[#This Row],[Trabajador]]) -> #REF! | G20: =IF(TablaPercepciones[[#This Row],[Percepción]]="","",VLOOKUP(TablaPercepciones[[#This Row],[Percepción]],Cat!$M$2:$N$42,2,0)) -> 38
A21: ENRIQUEZ CONSTANTINO SILVIA | B21: Otros ingresos por salarios | C21: 29 | D21: Previsión Social | E21: 0 | F21: =SUMIFS(#REF!,#REF!,TablaPercepciones[[#This Row],[Trabajador]]) -> #REF! | G21: =IF(TablaPercepciones[[#This Row],[Percepción]]="","",VLOOKUP(TablaPercepciones[[#This Row],[Percepción]],Cat!$M$2:$N$42,2,0)) -> 38
A22: GOMEZ HERNANDEZ SANTIAGO CRISTOBAL | B22: Otros ingresos por salarios | C22: 29 | D22: Previsión Social | E22: 0 | F22: =SUMIFS(#REF!,#REF!,TablaPercepciones[[#This Row],[Trabajador]]) -> #REF! | G22: =IF(TablaPercepciones[[#This Row],[Percepción]]="","",VLOOKUP(TablaPercepciones[[#This Row],[Percepción]],Cat!$M$2:$N$42,2,0)) -> 38
A23: GOMEZ LOPEZ JUAN | B23: Otros ingresos por salarios | C23: 29 | D23: Previsión Social | E23: 0 | F23: =SUMIFS(#REF!,#REF!,TablaPercepciones[[#This Row],[Trabajador]]) -> #REF! | G23: =IF(TablaPercepciones[[#This Row],[Percepción]]="","",VLOOKUP(TablaPercepciones[[#This Row],[Percepción]],Cat!$M$2:$N$42,2,0)) -> 38
A24: GONZALEZ ARCE EDUARDO | B24: Otros ingresos por salarios | C24: 29 | D24: Previsión Social | E24: 0 | F24: =SUMIFS(#REF!,#REF!,TablaPercepciones[[#This Row],[Trabajador]]) -> #REF! | G24: =IF(TablaPercepciones[[#This Row],[Percepción]]="","",VLOOKUP(TablaPercepciones[[#This Row],[Percepción]],Cat!$M$2:$N$42,2,0)) -> 38
A25: LEEP ARRIAGA SEMEIN AGUSTIN | B25: Otros ingresos por salarios | C25: 29 | D25: Previsión Social | E25: 0 | F25: =SUMIFS(#REF!,#REF!,TablaPercepciones[[#This Row],[Trabajador]]) -> #REF! | G25: =IF(TablaPercepciones[[#This Row],[Percepción]]="","",VLOOKUP(TablaPercepciones[[#This Row],[Percepción]],Cat!$M$2:$N$42,2,0)) -> 38
A26: LOPEZ MENDEZ LETICIA GUADALUPE | B26: Otros ingresos por salarios | C26: 29 | D26: Previsión Social | E26: 0 | F26: =SUMIFS(#REF!,#REF!,TablaPercepciones[[#This Row],[Trabajador]]) -> #REF! | G26: =IF(TablaPercepciones[[#This Row],[Percepción]]="","",VLOOKUP(TablaPercepciones[[#This Row],[Percepción]],Cat!$M$2:$N$42,2,0)) -> 38
A27: LOPEZ OVANDO LEANDRA GUADALUPE | B27: Otros ingresos por salarios | C27: 29 | D27: Previsión Social | E27: 0 | F27: =SUMIFS(#REF!,#REF!,TablaPercepciones[[#This Row],[Trabajador]]) -> #REF! | G27: =IF(TablaPercepciones[[#This Row],[Percepción]]="","",VLOOKUP(TablaPercepciones[[#This Row],[Percepción]],Cat!$M$2:$N$42,2,0)) -> 38
A28: MENDEZ SANCHEZ MIGUEL | B28: Otros ingresos por salarios | C28: 29 | D28: Previsión Social | E28: 0 | F28: =SUMIFS(#REF!,#REF!,TablaPercepciones[[#This Row],[Trabajador]]) -> #REF! | G28: =IF(TablaPercepciones[[#This Row],[Percepción]]="","",VLOOKUP(TablaPercepciones[[#This Row],[Percepción]],Cat!$M$2:$N$42,2,0)) -> 38
A29: NAJERA NAJERA GREGORIO CESAR | B29: Otros ingresos por salarios | C29: 29 | D29: Previsión Social | E29: 0 | F29: =SUMIFS(#REF!,#REF!,TablaPercepciones[[#This Row],[Trabajador]]) -> #REF! | G29: =IF(TablaPercepciones[[#This Row],[Percepción]]="","",VLOOKUP(TablaPercepciones[[#This Row],[Percepción]],Cat!$M$2:$N$42,2,0)) -> 38
A30: RAMIREZ CRUZ ANISETO | B30: Otros ingresos por salarios | C30: 29 | D30: Previsión Social | E30: 0 | F30: =SUMIFS(#REF!,#REF!,TablaPercepciones[[#This Row],[Trabajador]]) -> #REF! | G30: =IF(TablaPercepciones[[#This Row],[Percepción]]="","",VLOOKUP(TablaPercepciones[[#This Row],[Percepción]],Cat!$M$2:$N$42,2,0)) -> 38
A31: RAMOS CALVO IVAN ALEJANDRO | B31: Otros ingresos por salarios | C31: 29 | D31: Previsión Social | E31: 0 | F31: =SUMIFS(#REF!,#REF!,TablaPercepciones[[#This Row],[Trabajador]]) -> #REF! | G31: =IF(TablaPercepciones[[#This Row],[Percepción]]="","",VLOOKUP(TablaPercepciones[[#This Row],[Percepción]],Cat!$M$2:$N$42,2,0)) -> 38
... A37: YAÑEZ LOPEZ LORENA | B37: Otros ingresos por salarios | C37: 29 | D37: Previsión Social | E37: 0 | F37: =SUMIFS(#REF!,#REF!,TablaPercepciones[[#This Row],[Trabajador]]) -> #REF! | G37: =IF(TablaPercepciones[[#This Row],[Percepción]]="","",VLOOKUP(TablaPercepciones[[#This Row],[Percepción]],Cat!$M$2:$N$42,2,0)) -> 38
A38: CAMACHO OVANDO ALAN ULISES | B38: Sueldos, Salarios Rayas y Jornales | C38: 46 | D38: Compensación | E38: =SUMIFS(#REF!,#REF!,TablaPercepciones[[#This Row],[Trabajador]]) -> #REF! | F38: 0 | G38: =IF(TablaPercepciones[[#This Row],[Percepción]]="","",VLOOKUP(TablaPercepciones[[#This Row],[Percepción]],Cat!$M$2:$N$42,2,0)) -> 1
A39: ENRIQUEZ CONSTANTINO SILVIA | B39: Sueldos, Salarios Rayas y Jornales | C39: 46 | D39: Compensación | E39: =SUMIFS(#REF!,#REF!,TablaPercepciones[[#This Row],[Trabajador]]) -> #REF! | F39: 0 | G39: =IF(TablaPercepciones[[#This Row],[Percepción]]="","",VLOOKUP(TablaPercepciones[[#This Row],[Percepción]],Cat!$M$2:$N$42,2,0)) -> 1
A40: GOMEZ HERNANDEZ SANTIAGO CRISTOBAL | B40: Sueldos, Salarios Rayas y Jornales | C40: 46 | D40: Compensación | E40: =SUMIFS(#REF!,#REF!,TablaPercepciones[[#This Row],[Trabajador]]) -> #REF! | F40: 0 | G40: =IF(TablaPercepciones[[#This Row],[Percepción]]="","",VLOOKUP(TablaPercepciones[[#This Row],[Percepción]],Cat!$M$2:$N$42,2,0)) -> 1
A41: GOMEZ LOPEZ JUAN | B41: Sueldos, Salarios Rayas y Jornales | C41: 46 | D41: Compensación | E41: =SUMIFS(#REF!,#REF!,TablaPercepciones[[#This Row],[Trabajador]]) -> #REF! | F41: 0 | G41: =IF(TablaPercepciones[[#This Row],[Percepción]]="","",VLOOKUP(TablaPercepciones[[#This Row],[Percepción]],Cat!$M$2:$N$42,2,0)) -> 1
A42: GONZALEZ ARCE EDUARDO | B42: Sueldos, Salarios Rayas y Jornales | C42: 46 | D42: Compensación | E42: =SUMIFS(#REF!,#REF!,TablaPercepciones[[#This Row],[Trabajador]]) -> #REF! | F42: 0 | G42: =IF(TablaPercepciones[[#This Row],[Percepción]]="","",VLOOKUP(TablaPercepciones[[#This Row],[Percepción]],Cat!$M$2:$N$42,2,0)) -> 1
A43: LEEP ARRIAGA SEMEIN AGUSTIN | B43: Sueldos, Salarios Rayas y Jornales | C43: 46 | D43: Compensación | E43: =SUMIFS(#REF!,#REF!,TablaPercepciones[[#This Row],[Trabajador]]) -> #REF! | F43: 0 | G43: =IF(TablaPercepciones[[#This Row],[Percepción]]="","",VLOOKUP(TablaPercepciones[[#This Row],[Percepción]],Cat!$M$2:$N$42,2,0)) -> 1
A44: LOPEZ MENDEZ LETICIA GUADALUPE | B44: Sueldos, Salarios Rayas y Jornales | C44: 46 | D44: Compensación | E44: =SUMIFS(#REF!,#REF!,TablaPercepciones[[#This Row],[Trabajador]]) -> #REF! | F44: 0 | G44: =IF(TablaPercepciones[[#This Row],[Percepción]]="","",VLOOKUP(TablaPercepciones[[#This Row],[Percepción]],Cat!$M$2:$N$42,2,0)) -> 1
A45: LOPEZ OVANDO LEANDRA GUADALUPE | B45: Sueldos, Salarios Rayas y Jornales | C45: 46 | D45: Compensación | E45: =SUMIFS(#REF!,#REF!,TablaPercepciones[[#This Row],[Trabajador]]) -> #REF! | F45: 0 | G45: =IF(TablaPercepciones[[#This Row],[Percepción]]="","",VLOOKUP(TablaPercepciones[[#This Row],[Percepción]],Cat!$M$2:$N$42,2,0)) -> 1
A46: MENDEZ SANCHEZ MIGUEL | B46: Sueldos, Salarios Rayas y Jornales | C46: 46 | D46: Compensación | E46: =SUMIFS(#REF!,#REF!,TablaPercepciones[[#This Row],[Trabajador]]) -> #REF! | F46: 0 | G46: =IF(TablaPercepciones[[#This Row],[Percepción]]="","",VLOOKUP(TablaPercepciones[[#This Row],[Percepción]],Cat!$M$2:$N$42,2,0)) -> 1
A47: NAJERA NAJERA GREGORIO CESAR | B47: Sueldos, Salarios Rayas y Jornales | C47: 46 | D47: Compensación | E47: =SUMIFS(#REF!,#REF!,TablaPercepciones[[#This Row],[Trabajador]]) -> #REF! | F47: 0 | G47: =IF(TablaPercepciones[[#This Row],[Percepción]]="","",VLOOKUP(TablaPercepciones[[#This Row],[Percepción]],Cat!$M$2:$N$42,2,0)) -> 1
A48: RAMIREZ CRUZ ANISETO | B48: Sueldos, Salarios Rayas y Jornales | C48: 46 | D48: Compensación | E48: =SUMIFS(#REF!,#REF!,TablaPercepciones[[#This Row],[Trabajador]]) -> #REF! | F48: 0 | G48: =IF(TablaPercepciones[[#This Row],[Percepción]]="","",VLOOKUP(TablaPercepciones[[#This Row],[Percepción]],Cat!$M$2:$N$42,2,0)) -> 1
A49: RAMOS CALVO IVAN ALEJANDRO | B49: Sueldos, Salarios Rayas y Jornales | C49: 46 | D49: Compensación | E49: =SUMIFS(#REF!,#REF!,TablaPercepciones[[#This Row],[Trabajador]]) -> #REF! | F49: 0 | G49: =IF(TablaPercepciones[[#This Row],[Percepción]]="","",VLOOKUP(TablaPercepciones[[#This Row],[Percepción]],Cat!$M$2:$N$42,2,0)) -> 1
... A55: YAÑEZ LOPEZ LORENA | B55: Sueldos, Salarios Rayas y Jornales | C55: 46 | D55: Compensación | E55: =SUMIFS(#REF!,#REF!,TablaPercepciones[[#This Row],[Trabajador]]) -> #REF! | F55: 0 | G55: =IF(TablaPercepciones[[#This Row],[Percepción]]="","",VLOOKUP(TablaPercepciones[[#This Row],[Percepción]],Cat!$M$2:$N$42,2,0)) -> 1
A56: CAMACHO OVANDO ALAN ULISES | B56: Prima vacacional | C56: 41 | D56: PRIMA VACACIONAL | E56: =SUMIFS(#REF!,#REF!,TablaPercepciones[[#This Row],[Trabajador]])-TablaPercepciones[[#This Row],[o]] -> #REF! | F56: =IF(SUMIFS(#REF!,#REF!,TablaPercepciones[[#This Row],[Trabajador]])>1303.2,1303.2,0) -> #REF! | G56: =IF(TablaPercepciones[[#This Row],[Percepción]]="","",VLOOKUP(TablaPercepciones[[#This Row],[Percepción]],Cat!$M$2:$N$42,2,0)) -> 21
A57: ENRIQUEZ CONSTANTINO SILVIA | B57: Prima vacacional | C57: 41 | D57: PRIMA VACACIONAL | E57: =SUMIFS(#REF!,#REF!,TablaPercepciones[[#This Row],[Trabajador]])-TablaPercepciones[[#This Row],[o]] -> #REF! | F57: =IF(SUMIFS(#REF!,#REF!,TablaPercepciones[[#This Row],[Trabajador]])>1303.2,1303.2,0) -> #REF! | G57: =IF(TablaPercepciones[[#This Row],[Percepción]]="","",VLOOKUP(TablaPercepciones[[#This Row],[Percepción]],Cat!$M$2:$N$42,2,0)) -> 21
A58: GOMEZ HERNANDEZ SANTIAGO CRISTOBAL | B58: Prima vacacional | C58: 41 | D58: PRIMA VACACIONAL | E58: =SUMIFS(#REF!,#REF!,TablaPercepciones[[#This Row],[Trabajador]])-TablaPercepciones[[#This Row],[o]] -> #REF! | F58: =IF(SUMIFS(#REF!,#REF!,TablaPercepciones[[#This Row],[Trabajador]])>1303.2,1303.2,0) -> #REF! | G58: =IF(TablaPercepciones[[#This Row],[Percepción]]="","",VLOOKUP(TablaPercepciones[[#This Row],[Percepción]],Cat!$M$2:$N$42,2,0)) -> 21
A59: GOMEZ LOPEZ JUAN | B59: Prima vacacional | C59: 41 | D59: PRIMA VACACIONAL | E59: =SUMIFS(#REF!,#REF!,TablaPercepciones[[#This Row],[Trabajador]])-TablaPercepciones[[#This Row],[o]] -> #REF! | F59: =IF(SUMIFS(#REF!,#REF!,TablaPercepciones[[#This Row],[Trabajador]])>1303.2,1303.2,0) -> #REF! | G59: =IF(TablaPercepciones[[#This Row],[Percepción]]="","",VLOOKUP(TablaPercepciones[[#This Row],[Percepción]],Cat!$M$2:$N$42,2,0)) -> 21
A60: GONZALEZ ARCE EDUARDO | B60: Prima vacacional | C60: 41 | D60: PRIMA VACACIONAL | E60: =SUMIFS(#REF!,#REF!,TablaPercepciones[[#This Row],[Trabajador]])-TablaPercepciones[[#This Row],[o]] -> #REF! | F60: =IF(SUMIFS(#REF!,#REF!,TablaPercepciones[[#This Row],[Trabajador]])>1303.2,1303.2,0) -> #REF! | G60: =IF(TablaPercepciones[[#This Row],[Percepción]]="","",VLOOKUP(TablaPercepciones[[#This Row],[Percepción]],Cat!$M$2:$N$42,2,0)) -> 21
A61: LEEP ARRIAGA SEMEIN AGUSTIN | B61: Prima vacacional | C61: 41 | D61: PRIMA VACACIONAL | E61: =SUMIFS(#REF!,#REF!,TablaPercepciones[[#This Row],[Trabajador]])-TablaPercepciones[[#This Row],[o]] -> #REF! | F61: =IF(SUMIFS(#REF!,#REF!,TablaPercepciones[[#This Row],[Trabajador]])>1303.2,1303.2,0) -> #REF! | G61: =IF(TablaPercepciones[[#This Row],[Percepción]]="","",VLOOKUP(TablaPercepciones[[#This Row],[Percepción]],Cat!$M$2:$N$42,2,0)) -> 21
A62: LOPEZ MENDEZ LETICIA GUADALUPE | B62: Prima vacacional | C62: 41 | D62: PRIMA VACACIONAL | E62: =SUMIFS(#REF!,#REF!,TablaPercepciones[[#This Row],[Trabajador]])-TablaPercepciones[[#This Row],[o]] -> #REF! | F62: =IF(SUMIFS(#REF!,#REF!,TablaPercepciones[[#This Row],[Trabajador]])>1303.2,1303.2,0) -> #REF! | G62: =IF(TablaPercepciones[[#This Row],[Percepción]]="","",VLOOKUP(TablaPercepciones[[#This Row],[Percepción]],Cat!$M$2:$N$42,2,0)) -> 21
A63: LOPEZ OVANDO LEANDRA GUADALUPE | B63: Prima vacacional | C63: 41 | D63: PRIMA VACACIONAL | E63: =SUMIFS(#REF!,#REF!,TablaPercepciones[[#This Row],[Trabajador]])-TablaPercepciones[[#This Row],[o]] -> #REF! | F63: =IF(SUMIFS(#REF!,#REF!,TablaPercepciones[[#This Row],[Trabajador]])>1303.2,1303.2,0) -> #REF! | G63: =IF(TablaPercepciones[[#This Row],[Percepción]]="","",VLOOKUP(TablaPercepciones[[#This Row],[Percepción]],Cat!$M$2:$N$42,2,0)) -> 21
A64: MENDEZ SANCHEZ MIGUEL | B64: Prima vacacional | C64: 41 | D64: PRIMA VACACIONAL | E64: =SUMIFS(#REF!,#REF!,TablaPercepciones[[#This Row],[Trabajador]])-TablaPercepciones[[#This Row],[o]] -> #REF! | F64: =IF(SUMIFS(#REF!,#REF!,TablaPercepciones[[#This Row],[Trabajador]])>1303.2,1303.2,0) -> #REF! | G64: =IF(TablaPercepciones[[#This Row],[Percepción]]="","",VLOOKUP(TablaPercepciones[[#This Row],[Percepción]],Cat!$M$2:$N$42,2,0)) -> 21
A65: NAJERA NAJERA GREGORIO CESAR | B65: Prima vacacional | C65: 41 | D65: PRIMA VACACIONAL | E65: =SUMIFS(#REF!,#REF!,TablaPercepciones[[#This Row],[Trabajador]])-TablaPercepciones[[#This Row],[o]] -> #REF! | F65: =IF(SUMIFS(#REF!,#REF!,TablaPercepciones[[#This Row],[Trabajador]])>1303.2,1303.2,0) -> #REF! | G65: =IF(TablaPercepciones[[#This Row],[Percepción]]="","",VLOOKUP(TablaPercepciones[[#This Row],[Percepción]],Cat!$M$2:$N$42,2,0)) -> 21
A66: RAMIREZ CRUZ ANISETO | B66: Prima vacacional | C66: 41 | D66: PRIMA VACACIONAL | E66: =SUMIFS(#REF!,#REF!,TablaPercepciones[[#This Row],[Trabajador]])-TablaPercepciones[[#This Row],[o]] -> #REF! | F66: =IF(SUMIFS(#REF!,#REF!,TablaPercepciones[[#This Row],[Trabajador]])>1303.2,1303.2,0) -> #REF! | G66: =IF(TablaPercepciones[[#This Row],[Percepción]]="","",VLOOKUP(TablaPercepciones[[#This Row],[Percepción]],Cat!$M$2:$N$42,2,0)) -> 21
A67: RODRIGUEZ LEEP EUNICE ARODY | B67: Prima vacacional | C67: 41 | D67: PRIMA VACACIONAL | E67: =SUMIFS(#REF!,#REF!,TablaPercepciones[[#This Row],[Trabajador]])-TablaPercepciones[[#This Row],[o]] -> #REF! | F67: =IF(SUMIFS(#REF!,#REF!,TablaPercepciones[[#This Row],[Trabajador]])>1303.2,1303.2,0) -> #REF! | G67: =IF(TablaPercepciones[[#This Row],[Percepción]]="","",VLOOKUP(TablaPercepciones[[#This Row],[Percepción]],Cat!$M$2:$N$42,2,0)) -> 21
... A72: YAÑEZ LOPEZ LORENA | B72: Prima vacacional | C72: 41 | D72: PRIMA VACACIONAL | E72: =SUMIFS(#REF!,#REF!,TablaPercepciones[[#This Row],[Trabajador]])-TablaPercepciones[[#This Row],[o]] -> #REF! | F72: =IF(SUMIFS(#REF!,#REF!,TablaPercepciones[[#This Row],[Trabajador]])>1303.2,1303.2,0) -> #REF! | G72: =IF(TablaPercepciones[[#This Row],[Percepción]]="","",VLOOKUP(TablaPercepciones[[#This Row],[Percepción]],Cat!$M$2:$N$42,2,0)) -> 21
B77: Sueldos, Salarios Rayas y Jornales | C77: 1 | D77: Sueldos y Salarios | E77: 1
B78: Otros ingresos por salarios | C78: 29 | D78: Previsión Social | E78: 38
B79: Sueldos, Salarios Rayas y Jornales | C79: 46 | D79: Compensación | E79: 1
B80: Prima vacacional | C80: 41 | D80: PRIMA VACACIONAL | E80: 21

Sheet Deducciones
A1: Trabajador | B1: Deducción | C1: Clave | D1: Concepto | E1: Importe | F1: Clave Deducción
A2: CAMACHO OVANDO ALAN ULISES | B2: Otros | C2: 53 | D2: 5 % Cuota de Desplazamiento | E2: =SUMIFS(#REF!,#REF!,TablaDeducciones[[#This Row],[Trabajador]]) -> #REF! | F2: =IF(TablaDeducciones[[#This Row],[Deducción]]="","",VLOOKUP(TablaDeducciones[[#This Row],[Deducción]],Cat!$P$1:$Q$101,2,0)) -> 4
A3: GOMEZ HERNANDEZ SANTIAGO CRISTOBAL | B3: Otros | C3: 53 | D3: 5 % Cuota de Desplazamiento | E3: =SUMIFS(#REF!,#REF!,TablaDeducciones[[#This Row],[Trabajador]]) -> #REF! | F3: =IF(TablaDeducciones[[#This Row],[Deducción]]="","",VLOOKUP(TablaDeducciones[[#This Row],[Deducción]],Cat!$P$1:$Q$101,2,0)) -> 4
A4: GOMEZ LOPEZ JUAN | B4: Otros | C4: 53 | D4: 5 % Cuota de Desplazamiento | E4: =SUMIFS(#REF!,#REF!,TablaDeducciones[[#This Row],[Trabajador]]) -> #REF! | F4: =IF(TablaDeducciones[[#This Row],[Deducción]]="","",VLOOKUP(TablaDeducciones[[#This Row],[Deducción]],Cat!$P$1:$Q$101,2,0)) -> 4
A5: GONZALEZ ARCE EDUARDO | B5: Otros | C5: 53 | D5: 5 % Cuota de Desplazamiento | E5: =SUMIFS(#REF!,#REF!,TablaDeducciones[[#This Row],[Trabajador]]) -> #REF! | F5: =IF(TablaDeducciones[[#This Row],[Deducción]]="","",VLOOKUP(TablaDeducciones[[#This Row],[Deducción]],Cat!$P$1:$Q$101,2,0)) -> 4
A6: LEEP ARRIAGA SEMEIN AGUSTIN | B6: Otros | C6: 53 | D6: 5 % Cuota de Desplazamiento | E6: =SUMIFS(#REF!,#REF!,TablaDeducciones[[#This Row],[Trabajador]]) -> #REF! | F6: =IF(TablaDeducciones[[#This Row],[Deducción]]="","",VLOOKUP(TablaDeducciones[[#This Row],[Deducción]],Cat!$P$1:$Q$101,2,0)) -> 4
A7: LOPEZ MENDEZ LETICIA GUADALUPE | B7: Otros | C7: 53 | D7: 5 % Cuota de Desplazamiento | E7: =SUMIFS(#REF!,#REF!,TablaDeducciones[[#This Row],[Trabajador]]) -> #REF! | F7: =IF(TablaDeducciones[[#This Row],[Deducción]]="","",VLOOKUP(TablaDeducciones[[#This Row],[Deducción]],Cat!$P$1:$Q$101,2,0)) -> 4
A8: LOPEZ OVANDO LEANDRA GUADALUPE | B8: Otros | C8: 53 | D8: 5 % Cuota de Desplazamiento | E8: =SUMIFS(#REF!,#REF!,TablaDeducciones[[#This Row],[Trabajador]]) -> #REF! | F8: =IF(TablaDeducciones[[#This Row],[Deducción]]="","",VLOOKUP(TablaDeducciones[[#This Row],[Deducción]],Cat!$P$1:$Q$101,2,0)) -> 4
A9: MENDEZ SANCHEZ MIGUEL | B9: Otros | C9: 53 | D9: 5 % Cuota de Desplazamiento | E9: =SUMIFS(#REF!,#REF!,TablaDeducciones[[#This Row],[Trabajador]]) -> #REF! | F9: =IF(TablaDeducciones[[#This Row],[Deducción]]="","",VLOOKUP(TablaDeducciones[[#This Row],[Deducción]],Cat!$P$1:$Q$101,2,0)) -> 4
A10: RAMIREZ CRUZ ANISETO | B10: Otros | C10: 53 | D10: 5 % Cuota de Desplazamiento | E10: =SUMIFS(#REF!,#REF!,TablaDeducciones[[#This Row],[Trabajador]]) -> #REF! | F10: =IF(TablaDeducciones[[#This Row],[Deducción]]="","",VLOOKUP(TablaDeducciones[[#This Row],[Deducción]],Cat!$P$1:$Q$101,2,0)) -> 4
A11: RODRIGUEZ LEEP EUNICE ARODY | B11: Otros | C11: 53 | D11: 5 % Cuota de Desplazamiento | E11: =SUMIFS(#REF!,#REF!,TablaDeducciones[[#This Row],[Trabajador]]) -> #REF! | F11: =IF(TablaDeducciones[[#This Row],[Deducción]]="","",VLOOKUP(TablaDeducciones[[#This Row],[Deducción]],Cat!$P$1:$Q$101,2,0)) -> 4
A12: SANCHEZ CRUZ ISAAC RICARDO | B12: Otros | C12: 53 | D12: 5 % Cuota de Desplazamiento | E12: =SUMIFS(#REF!,#REF!,TablaDeducciones[[#This Row],[Trabajador]]) -> #REF! | F12: =IF(TablaDeducciones[[#This Row],[Deducción]]="","",VLOOKUP(TablaDeducciones[[#This Row],[Deducción]],Cat!$P$1:$Q$101,2,0)) -> 4
A13: SANCHEZ LOPEZ JOEL | B13: Otros | C13: 53 | D13: 5 % Cuota de Desplazamiento | E13: =SUMIFS(#REF!,#REF!,TablaDeducciones[[#This Row],[Trabajador]]) -> #REF! | F13: =IF(TablaDeducciones[[#This Row],[Deducción]]="","",VLOOKUP(TablaDeducciones[[#This Row],[Deducción]],Cat!$P$1:$Q$101,2,0)) -> 4
... A20: LOPEZ OVANDO LEANDRA GUADALUPE | B20: Pago por crédito de vivienda | C20: 57 | D20: INFONAVIT | E20: =SUMIFS(#REF!,#REF!,TablaDeducciones[[#This Row],[Trabajador]]) -> #REF! | F20: =IF(TablaDeducciones[[#This Row],[Deducción]]="","",VLOOKUP(TablaDeducciones[[#This Row],[Deducción]],Cat!$P$1:$Q$101,2,0)) -> 10

Sheet HorasExtra
A1: Trabajador | B1: Días | C1: Tipo de Horas | D1: Horas Extra | E1: Importe Pagado | F1: Clave Tipo de Horas
F2: =IF(TablaHorasExtra[Tipo de Horas]="","",VLOOKUP(TablaHorasExtra[Tipo de Horas],Cat!$S$1:$T$4,2,0))

Sheet OtrosPagos
A1: Trabajador | B1: Tipo de Otro Pago | C1: Clave | D1: Concepto | E1: Importe | F1: Clave de Tipo de Otro Pago | G1: SUBSIDIO CAUSADO
A2: CAMACHO OVANDO ALAN ULISES | B2: Subsidio para el empleo (efectivamente entregado al trabajador). | C2: 42 | D2: Subsidio para el Empleo | E2: =SUMIFS(#REF!,#REF!,TablaOtrosPagos[[#This Row],[Trabajador]]) -> #REF! | F2: =IF(TablaOtrosPagos[[#This Row],[Tipo de Otro Pago]]="","",VLOOKUP(TablaOtrosPagos[[#This Row],[Tipo de Otro Pago]],Cat!$V$1:$W$6,2,0)) -> 2 | G2: =LOOKUP(INDEX(TablaTrabajadores[Total Gravado],MATCH(TablaOtrosPagos[[#This Row],[Trabajador]],TablaTrabajadores[Nombre Trabajador],0)),'tablas isr art. 96'!$B$10:$B$20,'tablas isr art. 96'!$D$10:$D$20) -> #REF!
A3: ENRIQUEZ CONSTANTINO SILVIA | B3: Subsidio para el empleo (efectivamente entregado al trabajador). | C3: 42 | D3: Subsidio para el Empleo | E3: =SUMIFS(#REF!,#REF!,TablaOtrosPagos[[#This Row],[Trabajador]]) -> #REF! | F3: =IF(TablaOtrosPagos[[#This Row],[Tipo de Otro Pago]]="","",VLOOKUP(TablaOtrosPagos[[#This Row],[Tipo de Otro Pago]],Cat!$V$1:$W$6,2,0)) -> 2 | G3: =LOOKUP(INDEX(TablaTrabajadores[Total Gravado],MATCH(TablaOtrosPagos[[#This Row],[Trabajador]],TablaTrabajadores[Nombre Trabajador],0)),'tablas isr art. 96'!$B$10:$B$20,'tablas isr art. 96'!$D$10:$D$20) -> #REF!
A4: GOMEZ HERNANDEZ SANTIAGO CRISTOBAL | B4: Subsidio para el empleo (efectivamente entregado al trabajador). | C4: 42 | D4: Subsidio para el Empleo | E4: =SUMIFS(#REF!,#REF!,TablaOtrosPagos[[#This Row],[Trabajador]]) -> #REF! | F4: =IF(TablaOtrosPagos[[#This Row],[Tipo de Otro Pago]]="","",VLOOKUP(TablaOtrosPagos[[#This Row],[Tipo de Otro Pago]],Cat!$V$1:$W$6,2,0)) -> 2 | G4: =LOOKUP(INDEX(TablaTrabajadores[Total Gravado],MATCH(TablaOtrosPagos[[#This Row],[Trabajador]],TablaTrabajadores[Nombre Trabajador],0)),'tablas isr art. 96'!$B$10:$B$20,'tablas isr art. 96'!$D$10:$D$20) -> #REF!
A5: GOMEZ LOPEZ JUAN | B5: Subsidio para el empleo (efectivamente entregado al trabajador). | C5: 42 | D5: Subsidio para el Empleo | E5: =SUMIFS(#REF!,#REF!,TablaOtrosPagos[[#This Row],[Trabajador]]) -> #REF! | F5: =IF(TablaOtrosPagos[[#This Row],[Tipo de Otro Pago]]="","",VLOOKUP(TablaOtrosPagos[[#This Row],[Tipo de Otro Pago]],Cat!$V$1:$W$6,2,0)) -> 2 | G5: =LOOKUP(INDEX(TablaTrabajadores[Total Gravado],MATCH(TablaOtrosPagos[[#This Row],[Trabajador]],TablaTrabajadores[Nombre Trabajador],0)),'tablas isr art. 96'!$B$10:$B$20,'tablas isr art. 96'!$D$10:$D$20) -> #REF!
A6: GONZALEZ ARCE EDUARDO | B6: Subsidio para el empleo (efectivamente entregado al trabajador). | C6: 42 | D6: Subsidio para el Empleo | E6: =SUMIFS(#REF!,#REF!,TablaOtrosPagos[[#This Row],[Trabajador]]) -> #REF! | F6: =IF(TablaOtrosPagos[[#This Row],[Tipo de Otro Pago]]="","",VLOOKUP(TablaOtrosPagos[[#This Row],[Tipo de Otro Pago]],Cat!$V$1:$W$6,2,0)) -> 2 | G6: =LOOKUP(INDEX(TablaTrabajadores[Total Gravado],MATCH(TablaOtrosPagos[[#This Row],[Trabajador]],TablaTrabajadores[Nombre Trabajador],0)),'tablas isr art. 96'!$B$10:$B$20,'tablas isr art. 96'!$D$10:$D$20) -> #REF!
A7: LEEP ARRIAGA SEMEIN AGUSTIN | B7: Subsidio para el empleo (efectivamente entregado al trabajador). | C7: 42 | D7: Subsidio para el Empleo | E7: =SUMIFS(#REF!,#REF!,TablaOtrosPagos[[#This Row],[Trabajador]]) -> #REF! | F7: =IF(TablaOtrosPagos[[#This Row],[Tipo de Otro Pago]]="","",VLOOKUP(TablaOtrosPagos[[#This Row],[Tipo de Otro Pago]],Cat!$V$1:$W$6,2,0)) -> 2 | G7: =LOOKUP(INDEX(TablaTrabajadores[Total Gravado],MATCH(TablaOtrosPagos[[#This Row],[Trabajador]],TablaTrabajadores[Nombre Trabajador],0)),'tablas isr art. 96'!$B$10:$B$20,'tablas isr art. 96'!$D$10:$D$20) -> #REF!
A8: LOPEZ MENDEZ LETICIA GUADALUPE | B8: Subsidio para el empleo (efectivamente entregado al trabajador). | C8: 42 | D8: Subsidio para el Empleo | E8: =SUMIFS(#REF!,#REF!,TablaOtrosPagos[[#This Row],[Trabajador]]) -> #REF! | F8: =IF(TablaOtrosPagos[[#This Row],[Tipo de Otro Pago]]="","",VLOOKUP(TablaOtrosPagos[[#This Row],[Tipo de Otro Pago]],Cat!$V$1:$W$6,2,0)) -> 2 | G8: =LOOKUP(INDEX(TablaTrabajadores[Total Gravado],MATCH(TablaOtrosPagos[[#This Row],[Trabajador]],TablaTrabajadores[Nombre Trabajador],0)),'tablas isr art. 96'!$B$10:$B$20,'tablas isr art. 96'!$D$10:$D$20) -> #REF!
A9: LOPEZ OVANDO LEANDRA GUADALUPE | B9: Subsidio para el empleo (efectivamente entregado al trabajador). | C9: 42 | D9: Subsidio para el Empleo | E9: =SUMIFS(#REF!,#REF!,TablaOtrosPagos[[#This Row],[Trabajador]]) -> #REF! | F9: =IF(TablaOtrosPagos[[#This Row],[Tipo de Otro Pago]]="","",VLOOKUP(TablaOtrosPagos[[#This Row],[Tipo de Otro Pago]],Cat!$V$1:$W$6,2,0)) -> 2 | G9: =LOOKUP(INDEX(TablaTrabajadores[Total Gravado],MATCH(TablaOtrosPagos[[#This Row],[Trabajador]],TablaTrabajadores[Nombre Trabajador],0)),'tablas isr art. 96'!$B$10:$B$20,'tablas isr art. 96'!$D$10:$D$20) -> #REF!
A10: MENDEZ SANCHEZ MIGUEL | B10: Subsidio para el empleo (efectivamente entregado al trabajador). | C10: 42 | D10: Subsidio para el Empleo | E10: =SUMIFS(#REF!,#REF!,TablaOtrosPagos[[#This Row],[Trabajador]]) -> #REF! | F10: =IF(TablaOtrosPagos[[#This Row],[Tipo de Otro Pago]]="","",VLOOKUP(TablaOtrosPagos[[#This Row],[Tipo de Otro Pago]],Cat!$V$1:$W$6,2,0)) -> 2 | G10: =LOOKUP(INDEX(TablaTrabajadores[Total Gravado],MATCH(TablaOtrosPagos[[#This Row],[Trabajador]],TablaTrabajadores[Nombre Trabajador],0)),'tablas isr art. 96'!$B$10:$B$20,'tablas isr art. 96'!$D$10:$D$20) -> #REF!
A11: NAJERA NAJERA GREGORIO CESAR | B11: Subsidio para el empleo (efectivamente entregado al trabajador). | C11: 42 | D11: Subsidio para el Empleo | E11: =SUMIFS(#REF!,#REF!,TablaOtrosPagos[[#This Row],[Trabajador]]) -> #REF! | F11: =IF(TablaOtrosPagos[[#This Row],[Tipo de Otro Pago]]="","",VLOOKUP(TablaOtrosPagos[[#This Row],[Tipo de Otro Pago]],Cat!$V$1:$W$6,2,0)) -> 2 | G11: =LOOKUP(INDEX(TablaTrabajadores[Total Gravado],MATCH(TablaOtrosPagos[[#This Row],[Trabajador]],TablaTrabajadores[Nombre Trabajador],0)),'tablas isr art. 96'!$B$10:$B$20,'tablas isr art. 96'!$D$10:$D$20) -> #REF!
A12: RAMIREZ CRUZ ANISETO | B12: Subsidio para el empleo (efectivamente entregado al trabajador). | C12: 42 | D12: Subsidio para el Empleo | E12: =SUMIFS(#REF!,#REF!,TablaOtrosPagos[[#This Row],[Trabajador]]) -> #REF! | F12: =IF(TablaOtrosPagos[[#This Row],[Tipo de Otro Pago]]="","",VLOOKUP(TablaOtrosPagos[[#This Row],[Tipo de Otro Pago]],Cat!$V$1:$W$6,2,0)) -> 2 | G12: =LOOKUP(INDEX(TablaTrabajadores[Total Gravado],MATCH(TablaOtrosPagos[[#This Row],[Trabajador]],TablaTrabajadores[Nombre Trabajador],0)),'tablas isr art. 96'!$B$10:$B$20,'tablas isr art. 96'!$D$10:$D$20) -> #REF!
A13: RAMOS CALVO IVAN ALEJANDRO | B13: Subsidio para el empleo (efectivamente entregado al trabajador). | C13: 42 | D13: Subsidio para el Empleo | E13: =SUMIFS(#REF!,#REF!,TablaOtrosPagos[[#This Row],[Trabajador]]) -> #REF! | F13: =IF(TablaOtrosPagos[[#This Row],[Tipo de Otro Pago]]="","",VLOOKUP(TablaOtrosPagos[[#This Row],[Tipo de Otro Pago]],Cat!$V$1:$W$6,2,0)) -> 2 | G13: =LOOKUP(INDEX(TablaTrabajadores[Total Gravado],MATCH(TablaOtrosPagos[[#This Row],[Trabajador]],TablaTrabajadores[Nombre Trabajador],0)),'tablas isr art. 96'!$B$10:$B$20,'tablas isr art. 96'!$D$10:$D$20) -> #REF!
... A19: YAÑEZ LOPEZ LORENA | B19: Subsidio para el empleo (efectivamente entregado al trabajador). | C19: 42 | D19: Subsidio para el Empleo | E19: =SUMIFS(#REF!,#REF!,TablaOtrosPagos[[#This Row],[Trabajador]]) -> #REF! | F19: =IF(TablaOtrosPagos[[#This Row],[Tipo de Otro Pago]]="","",VLOOKUP(TablaOtrosPagos[[#This Row],[Tipo de Otro Pago]],Cat!$V$1:$W$6,2,0)) -> 2 | G19: =LOOKUP(INDEX(TablaTrabajadores[Total Gravado],MATCH(TablaOtrosPagos[[#This Row],[Trabajador]],TablaTrabajadores[Nombre Trabajador],0)),'tablas isr art. 96'!$B$10:$B$20,'tablas isr art. 96'!$D$10:$D$20) -> #REF!

Sheet Cat
A1: Tipo de Nómina | B1: Descripción | D1: Descripción | E1: c_PeriodicidadPago | G1: Descripción | H1: c_TipoContrato | J1: Descripción | K1: c_TipoRegimen | M1: Descripción | N1: c_TipoPercepcion | P1: Descripción | Q1: c_TipoDeduccion | S1: Descripción | T1: c_TipoHoras | V1: Descripción | W1: c_TipoOtroPago | Y1: Descripción | Z1: c_OrigenRecurso | AB1: Nombre del estado | AC1: c_Estado | AD1: c_Pais | AF1: Descripción | AG1: c_RegimenFiscal | AI1: Sindicato | AK1: Descripción | AL1: c_TipoJornada
A2: Nómina Ordinaria | B2: O | D2: Diario | E2: 1 | G2: Contrato de trabajo por tiempo indeterminado | H2: 1 | J2: Sueldos | K2: 2 | M2: Sueldos, Salarios Rayas y Jornales | N2: 1 | P2: Seguridad social | Q2: 1 | S2: Dobles | T2: 1 | V2: Reintegro de ISR pagado en exceso (siempre que no haya sido enterado al SAT). | W2: 1 | Y2: Ingresos propios | Z2: IP | AB2: Aguascalientes | AC2: AGU | AD2: MEX | AF2: General de Ley Personas Morales | AG2: 601 | AI2: Sí | AK2: Diurna | AL2: 1
A3: Nómina Extraordinaria | B3: E | D3: Semanal | E3: 2 | G3: Contrato de trabajo para obra determinada | H3: 2 | J3: Jubilados | K3: 3 | M3: Gratificación Anual (Aguinaldo) | N3: 2 | P3: ISR | Q3: 2 | S3: Triples | T3: 2 | V3: Subsidio para el empleo (efectivamente entregado al trabajador). | W3: 2 | Y3: Ingreso federales | Z3: IF | AB3: Baja California | AC3: BCN | AD3: MEX | AF3: Personas Morales con Fines no Lucrativos | AG3: 603 | AI3: No | AK3: Nocturna | AL3: 2
D4: Catorcenal | E4: 3 | G4: Contrato de trabajo por tiempo determinado | H4: 3 | J4: Pensionados | K4: 4 | M4: Participación de los Trabajadores en las Utilidades PTU | N4: 3 | P4: Aportaciones a retiro, cesantía en edad avanzada y vejez. | Q4: 3 | S4: Simples | T4: 3 | V4: Viáticos (entregados al trabajador). | W4: 3 | Y4: Ingresos mixtos | Z4: IM | AB4: Baja California Sur | AC4: BCS | AD4: MEX | AF4: Sueldos y Salarios e Ingresos Asimilados a Salarios | AG4: 605 | AK4: Mixta | AL4: 3
D5: Quincenal | E5: 4 | G5: Contrato de trabajo por temporada | H5: 4 | J5: Asimilados Miembros Sociedades Cooperativas Produccion | K5: 5 | M5: Reembolso de Gastos Médicos Dentales y Hospitalarios | N5: 4 | P5: Otros | Q5: 4 | V5: Aplicación de saldo a favor por compensación anual. | W5: 4 | AB5: Campeche | AC5: CAM | AD5: MEX | AF5: Arrendamiento | AG5: 606 | AK5: Por hora | AL5: 4
D6: Mensual | E6: 5 | G6: Contrato de trabajo sujeto a prueba | H6: 5 | J6: Asimilados Integrantes Sociedades Asociaciones Civiles | K6: 6 | M6: Fondo de Ahorro | N6: 5 | P6: Aportaciones a Fondo de vivienda | Q6: 5 | V6: Pagos distintos a los listados y que no deben considerarse como ingreso por sueldos, salarios o ingresos asimilados. | W6: 999 | AB6: Chiapas | AC6: CHP | AD6: MEX | AF6: Demás ingresos | AG6: 608 | AK6: Reducida | AL6: 5
D7: Bimestral | E7: 6 | G7: Contrato de trabajo con capacitación inicial | H7: 6 | J7: Asimilados Miembros consejos | K7: 7 | M7: Caja de ahorro | N7: 6 | P7: Descuento por incapacidad | Q7: 6 | AB7: Chihuahua | AC7: CHH | AD7: MEX | AF7: Consolidación | AG7: 609 | AK7: Continuada | AL7: 6
D8: Unidad obra | E8: 7 | G8: Modalidad de contratación por pago de hora laborada | H8: 7 | J8: Asimilados comisionistas | K8: 8 | M8: Contribuciones a Cargo del Trabajador Pagadas por el Patrón | N8: 9 | P8: Pensión alimenticia | Q8: 7 | AB8: Coahuila | AC8: COA | AD8: MEX | AF8: Residentes en el Extranjero sin Establecimiento Permanente en México | AG8: 610 | AK8: Partida | AL8: 7
D9: Comisión | E9: 8 | G9: Modalidad de trabajo por comisión laboral | H9: 8 | J9: Asimilados Honorarios | K9: 9 | M9: Premios por puntualidad | N9: 10 | P9: Renta | Q9: 8 | AB9: Colima | AC9: COL | AD9: MEX | AF9: Ingresos por Dividendos (socios y accionistas) | AG9: 611 | AK9: Por turnos | AL9: 8
D10: Precio alzado | E10: 9 | G10: Modalidades de contratación donde no existe relación de trabajo | H10: 9 | J10: Asimilados acciones | K10: 10 | M10: Prima de Seguro de vida | N10: 11 | P10: Préstamos provenientes del Fondo Nacional de la Vivienda para los Trabajadores | Q10: 9 | AB10: Ciudad de México | AC10: DIF | AD10: MEX | AF10: Personas Físicas con Actividades Empresariales y Profesionales | AG10: 612 | AK10: Otra Jornada | AL10: 99
D11: Decenal | E11: 10 | G11: Jubilación, pensión, retiro. | H11: 10 | J11: Asimilados otros | K11: 11 | M11: Seguro de Gastos Médicos Mayores | N11: 12 | P11: Pago por crédito de vivienda | Q11: 10 | AB11: Durango | AC11: DUR | AD11: MEX | AF11: Ingresos por intereses | AG11: 614
D12: Otra Periodicidad | E12: 99 | G12: Otro contrato | H12: 99 | J12: Jubilados o Pensionados | K12: 12 | M12: Cuotas Sindicales Pagadas por el Patrón | N12: 13 | P12: Pago de abonos INFONACOT | Q12: 11 | AB12: Guanajuato | AC12: GUA | AD12: MEX | AF12: Sin obligaciones fiscales | AG12: 616
J13: Otro Regimen | K13: 99 | M13: Subsidios por incapacidad | N13: 14 | P13: Anticipo de salarios | Q13: 12 | AB13: Guerrero | AC13: GRO | AD13: MEX | AF13: Sociedades Cooperativas de Producción que optan por diferir sus ingresos | AG13: 620
M14: Becas para trabajadores y/o hijos | N14: 15 | P14: Pagos hechos con exceso al trabajador | Q14: 13 | AB14: Hidalgo | AC14: HID | AD14: MEX | AF14: Incorporación Fiscal | AG14: 621
M15: Horas extra | N15: 19 | P15: Errores | Q15: 14 | AB15: Jalisco | AC15: JAL | AD15: MEX | AF15: Actividades Agrícolas, Ganaderas, Silvícolas y Pesqueras | AG15: 622
M16: Prima dominical | N16: 20 | P16: Pérdidas | Q16: 15 | AB16: Estado de México | AC16: MEX | AD16: MEX | AF16: Opcional para Grupos de Sociedades | AG16: 623
M17: Prima vacacional | N17: 21 | P17: Averías | Q17: 16 | AB17: Michoacán | AC17: MIC | AD17: MEX | AF17: Coordinados | AG17: 624
M18: Prima por antigüedad | N18: 22 | P18: Adquisición de artículos producidos por la empresa o establecimiento | Q18: 17 | AB18: Morelos | AC18: MOR | AD18: MEX | AF18: Hidrocarburos | AG18: 628
M19: Pagos por separación | N19: 23 | P19: Cuotas para la constitución y fomento de sociedades cooperativas y de cajas de ahorro | Q19: 18 | AB19: Nayarit | AC19: NAY | AD19: MEX | AF19: Régimen de Enajenación o Adquisición de Bienes | AG19: 607
M20: Seguro de retiro | N20: 24 | P20: Cuotas sindicales | Q20: 19 | AB20: Nuevo León | AC20: NLE | AD20: MEX | AF20: De los Regímenes Fiscales Preferentes y de las Empresas Multinacionales | AG20: 629
M21: Indemnizaciones | N21: 25 | P21: Ausencia (Ausentismo) | Q21: 20 | AB21: Oaxaca | AC21: OAX | AD21: MEX | AF21: Enajenación de acciones en bolsa de valores | AG21: 630
M22: Reembolso por funeral | N22: 26 | P22: Cuotas obrero patronales | Q22: 21 | AB22: Puebla | AC22: PUE | AD22: MEX | AF22: Régimen de los ingresos por obtención de premios | AG22: 615
M23: Cuotas de seguridad social pagadas por el patrón | N23: 27 | P23: Impuestos Locales | Q23: 22 | AB23: Querétaro | AC23: QUE | AD23: MEX
M24: Comisiones | N24: 28 | P24: Aportaciones voluntarias | Q24: 23 | AB24: Quintana Roo | AC24: ROO | AD24: MEX
M25: Vales de despensa | N25: 29 | P25: Ajuste en Gratificación Anual (Aguinaldo) Exento | Q25: 24 | AB25: San Luis Potosí | AC25: SLP | AD25: MEX
M26: Vales de restaurante | N26: 30 | P26: Ajuste en Gratificación Anual (Aguinaldo) Gravado | Q26: 25 | AB26: Sinaloa | AC26: SIN | AD26: MEX
M27: Vales de gasolina | N27: 31 | P27: Ajuste en Participación de los Trabajadores en las Utilidades PTU Exento | Q27: 26 | AB27: Sonora | AC27: SON | AD27: MEX
M28: Vales de ropa | N28: 32 | P28: Ajuste en Participación de los Trabajadores en las Utilidades PTU Gravado | Q28: 27 | AB28: Tabasco | AC28: TAB | AD28: MEX
M29: Ayuda para renta | N29: 33 | P29: Ajuste en Reembolso de Gastos Médicos Dentales y Hospitalarios Exento | Q29: 28 | AB29: Tamaulipas | AC29: TAM | AD29: MEX
M30: Ayuda para artículos escolares | N30: 34 | P30: Ajuste en Fondo de ahorro Exento | Q30: 29 | AB30: Tlaxcala | AC30: TLA | AD30: MEX
M31: Ayuda para anteojos | N31: 35 | P31: Ajuste en Caja de ahorro Exento | Q31: 30 | AB31: Veracruz | AC31: VER | AD31: MEX
M32: Ayuda para transporte | N32: 36 | P32: Ajuste en Contribuciones a Cargo del Trabajador Pagadas por el Patrón Exento | Q32: 31 | AB32: Yucatán | AC32: YUC | AD32: MEX
M33: Ayuda para gastos de funeral | N33: 37 | P33: Ajuste en Premios por puntualidad Gravado | Q33: 32 | AB33: Zacatecas | AC33: ZAC | AD33: MEX
M34: Otros ingresos por salarios | N34: 38 | P34: Ajuste en Prima de Seguro de vida Exento | Q34: 33
M35: Jubilaciones, pensiones o haberes de retiro | N35: 39 | P35: Ajuste en Seguro de Gastos Médicos Mayores Exento | Q35: 34
M36: Jubilaciones, pensiones o haberes de retiro en parcialidades | N36: 44 | P36: Ajuste en Cuotas Sindicales Pagadas por el Patrón Exento | Q36: 35
M37: Ingresos en acciones o títulos valor que representan bienes | N37: 45 | P37: Ajuste en Subsidios por incapacidad Exento | Q37: 36
M38: Ingresos asimilados a salarios | N38: 046 | P38: Ajuste en Becas para trabajadores y/o hijos Exento | Q38: 37
M39: Alimentación | N39: 047 | P39: Ajuste en Horas extra Exento | Q39: 38
M40: Habitación | N40: 48 | P40: Ajuste en Horas extra Gravado | Q40: 39
M41: Premios por asistencia | N41: 49 | P41: Ajuste en Prima dominical Exento | Q41: 40
M42: Viáticos | N42: 50 | P42: Ajuste en Prima dominical Gravado | Q42: 41
P43: Ajuste en Prima vacacional Exento | Q43: 42
P44: Ajuste en Prima vacacional Gravado | Q44: 43
P45: Ajuste en Prima por antigüedad Exento | Q45: 44
P46: Ajuste en Prima por antigüedad Gravado | Q46: 45
P47: Ajuste en Pagos por separación Exento | Q47: 46
P48: Ajuste en Pagos por separación Gravado | Q48: 47
P49: Ajuste en Seguro de retiro Exento | Q49: 48
P50: Ajuste en Indemnizaciones Exento | Q50: 49
P51: Ajuste en Indemnizaciones Gravado | Q51: 50
P52: Ajuste en Reembolso por funeral Exento | Q52: 51
P53: Ajuste en Cuotas de seguridad social pagadas por el patrón Exento | Q53: 52
P54: Ajuste en Comisiones Gravado | Q54: 53
... P82: Ajuste en Viáticos (entregados al trabajador) | Q82: 81
P83: Ajuste en Fondo de ahorro Gravado | Q83: 082
P84: Ajuste en Caja de ahorro Gravado | Q84: 083
P85: Ajuste en Prima de Seguro de vida Gravado | Q85: 084
P86: Ajuste en Seguro de Gastos Médicos Mayores Gravado | Q86: 085
P87: Ajuste en Subsidios por incapacidad Gravado | Q87: 086
P88: Ajuste en Becas para trabajadores y/o hijos Gravado | Q88: 087
P89: Ajuste en Seguro de retiro Gravado | Q89: 088
P90: Ajuste en Vales de despensa Gravado | Q90: 089
P91: Ajuste en Vales de restaurante Gravado | Q91: 090
P92: Ajuste en Vales de gasolina Gravado | Q92: 091
P93: Ajuste en Vales de ropa Gravado | Q93: 092
P94: Ajuste en Ayuda para renta Gravado | Q94: 093
... P100: Ajuste a ingresos por sueldos y salarios gravados | Q100: 099
P101: Ajuste en Viáticos exentos | Q101: 100

Sheet tablas isr art. 96
B6: Tarifas 2021 DOF 11-01-2021
B7: TABLA DE SUBSIDIO PARA EL EMPLEO
B8: Monto de ingresos que sirven de base para calcular el impuesto
B9: Para ingresos de $ | C9: Hasta Ingresos de $ | D9: Cantidad de subsidio para el empleo 15 DIAS $
B10: 0.01 | C10: 1768.96 | D10: 407.02
B11: =+C10+0.01 -> 1768.97 | C11: 2653.8 | D11: 406.83
B12: =+C11+0.01 -> 2653.81 | C12: 3472.84 | D12: 406.62
B13: =+C12+0.01 -> 3472.85 | C13: 3537.87 | D13: 392.77
B14: =+C13+0.01 -> 3537.88 | C14: 4446.15 | D14: 382.46
B15: =+C14+0.01 -> 4446.16 | C15: 3417.18 | D15: 354.23
B16: =+C15+0.01 -> 3417.19 | C16: 5335.42 | D16: 324.87
B17: =+C16+0.01 -> 5335.43 | C17: 6224.67 | D17: 294.63
B18: =+C17+0.01 -> 6224.68 | C18: 7113.9 | D18: 253.54
B19: =+C18+0.01 -> 7113.91 | C19: 7382.33 | D19: 217.61
B20: =+C19+0.01 -> 7382.34 | C20: 1e+09 | D20: 0
